Workbook

Sheet Dashboard
B2: Dashboard — Indicadores por Instrutor
B4: Instrutor | C4: Qtde Treinamentos | D4: Custo Total (R$) | E4: Custo Médio por Treinamento (R$)
B5: Betânia Cayret Pregnolato | C5: =COUNTIF(Treinamentos_Feitos!$B$2:$B$2000,"*"&B5&"*") -> 86 | D5: =SUMIF(Treinamentos_Feitos!$B$2:$B$2000,"*"&B5&"*",Treinamentos_Feitos!$H$2:$H$2000) -> 43473.29 | E5: =IFERROR(D5/C5,0) -> 505.50337
B6: Bruno Souza | C6: =COUNTIF(Treinamentos_Feitos!$B$2:$B$2000,"*"&B6&"*") -> 106 | D6: =SUMIF(Treinamentos_Feitos!$B$2:$B$2000,"*"&B6&"*",Treinamentos_Feitos!$H$2:$H$2000) -> 54632.89 | E6: =IFERROR(D6/C6,0) -> 515.40462
B7: Carla Fernandes Dionizio | C7: =COUNTIF(Treinamentos_Feitos!$B$2:$B$2000,"*"&B7&"*") -> 61 | D7: =SUMIF(Treinamentos_Feitos!$B$2:$B$2000,"*"&B7&"*",Treinamentos_Feitos!$H$2:$H$2000) -> 30988.71 | E7: =IFERROR(D7/C7,0) -> 508.01164
B8: Isabela Paim Ricardo | C8: =COUNTIF(Treinamentos_Feitos!$B$2:$B$2000,"*"&B8&"*") -> 156 | D8: =SUMIF(Treinamentos_Feitos!$B$2:$B$2000,"*"&B8&"*",Treinamentos_Feitos!$H$2:$H$2000) -> 81042.31 | E8: =IFERROR(D8/C8,0) -> 519.50199
B9: Leonardo da Silva Azevedo | C9: =COUNTIF(Treinamentos_Feitos!$B$2:$B$2000,"*"&B9&"*") -> 269 | D9: =SUMIF(Treinamentos_Feitos!$B$2:$B$2000,"*"&B9&"*",Treinamentos_Feitos!$H$2:$H$2000) -> 135467.41 | E9: =IFERROR(D9/C9,0) -> 503.59632
B10: Roberta de Cássia Martareli | C10: =COUNTIF(Treinamentos_Feitos!$B$2:$B$2000,"*"&B10&"*") -> 204 | D10: =SUMIF(Treinamentos_Feitos!$B$2:$B$2000,"*"&B10&"*",Treinamentos_Feitos!$H$2:$H$2000) -> 101461.01 | E10: =IFERROR(D10/C10,0) -> 497.35789
B11: Lucas Silva dos Santos | C11: =COUNTIF(Treinamentos_Feitos!$B$2:$B$2000,"*"&B11&"*") -> 133 | D11: =SUMIF(Treinamentos_Feitos!$B$2:$B$2000,"*"&B11&"*",Treinamentos_Feitos!$H$2:$H$2000) -> 61758.48 | E11: =IFERROR(D11/C11,0) -> 464.34947
B13: Total geral | C13: =SUM(C5:C11) -> 1015 | D13: =SUM(D5:D11) -> 508824.1
B15: Lojas no pipeline de inauguração (por Status)
B16: Contrato | C16: =COUNTIF(Previsao_Inauguracao!$A$2:$A$1000,B16) -> 25
B17: Descontinuada | C17: =COUNTIF(Previsao_Inauguracao!$A$2:$A$1000,B17) -> 1
B18: Implantação | C18: =COUNTIF(Previsao_Inauguracao!$A$2:$A$1000,B18) -> 11
B19: Negociação | C19: =COUNTIF(Previsao_Inauguracao!$A$2:$A$1000,B19) -> 63
B20: Obra | C20: =COUNTIF(Previsao_Inauguracao!$A$2:$A$1000,B20) -> 35
B21: PNE | C21: =COUNTIF(Previsao_Inauguracao!$A$2:$A$1000,B21) -> 17

Sheet LEIA-ME
B2: Base Unificada — Instrutores AmPm x Rede de Lojas x Treinamentos x Inaugurações
B4: O que este arquivo faz:
B5: Cruza os 4 arquivos enviados numa única base, usando como chave o nome do instrutor
B6: (normalizado e casado por similaridade entre ID_AUVO / ID_CAJU / ID_UBER / nome completo)
B7: e o código PV Abadi para ligar lojas, treinamentos e inaugurações previstas.
B9: Abas:
B10: Instrutores - cadastro único consolidado (ativos e inativos)
B11: Treinamentos_Feitos - histórico de treinamentos já realizados, com instrutor unificado e custo por linha
B12: Rede_de_Lojas - base gerencial completa da rede (1.566 lojas ativas)
B13: Previsao_Inauguracao - pipeline de novas lojas/inaugurações e dias de treinamento necessários
B14: Recomendacao_Deslocamento - para cada loja do pipeline, os 3 instrutores ativos mais próximos
B15: Agenda_Semanal_Sugerida - agenda por instrutor, semana a semana, já roteirizada por proximidade
... B45: de PROXIMIDADE (quem está mais perto), não como custo final em R$.

Sheet Instrutores
A1: instr_id | B1: ID_UNICO | C1: ID_AUVO | D1: ID_CAJU | E1: ID_UBER | F1: NOME_COMPLETO | G1: TELEFONE | H1: EMAIL | I1: ENDERECO | J1: CPF | K1: STATUS | L1: Cidade | M1: UF | N1: Latitude | O1: Longitude
A2: 1 | B2: Betânia Pregnolato | C2: Betânia Pregnolato | D2: Betania Cayret Pregnolato | E2: Betania Cayret Pregnolato | F2: Betânia Cayret Pregnolato | G2: (11) 99351-1743 | H2: betania.ampm@igtgroup-ext.com.br | I2: Rua Manuel da Cunha Azevedo, nº 53, VILA GRANADA , São Paulo - SP // CEP: 03623-050 | J2: 126.130.838-75 | K2: Ativo | L2: São Paulo | M2: SP | N2: -23.5329 | O2: -46.6395
A3: 2 | B3: Bruno Ferreira | C3: Bruno Ferreira | D3: Bruno Ferreira De Souza | E3: Bruno Souza | F3: Bruno Souza | G3: (11) 99596-6401 | H3: bruno.ampm@igtgroup-ext.com.br | I3: RUA MAR VERMELHO,798 JD REGINA ALICE - BARUERI - SP, CEP 06412140 | J3: 360089058/14 | K3: Ativo | L3: Barueri | M3: SP | N3: -23.5057 | O3: -46.879
A4: 3 | B4: Carla Dionizio | C4: Carla Dionizio | D4: Carla Fernandes Dionizio | E4: Carla Fernandes Dionizio | F4: Carla Fernandes Dionizio | G4: (11) 98744-7398 | H4: carla.ampm@igtgroup-ext.com.br | I4: Rua Visconde de Ribamar, 125 A, Jardim Capela, São Paulo - SP // CEP: 04960-100 | J4: 327.521.458-61 | K4: Ativo | L4: São Paulo | M4: SP | N4: -23.5329 | O4: -46.6395
A5: 4 | B5: Isabela Paim | C5: Isabela Paim | D5: Isabela Paim Ricardo | E5: Isabela Paim | F5: Isabela Paim Ricardo | G5: (21) 99390-7088 | H5: isabela.ampm@igtgroup-ext.com.br | I5: Rua Garzon 62 JD LG 1 CA 11 LAGOA | J5: 786.909.007-72 | K5: Ativo | L5: Rio de Janeiro | M5: RJ | N5: -22.9129 | O5: -43.2003
A6: 5 | B6: Leonardo Azevedo | C6: Leonardo Azevedo | D6: Leonardo Da Silva Azevedo | E6: Leonardo Azevedo | F6: Leonardo da Silva Azevedo | G6: (53) 8112-3384 | H6: leonardo.ampm@igtgroup-ext.com.br | I6: Rua Val Porto, 223, Salgado filho, cep 96202-700 - RS | J6: 646.916.400-53 | K6: Ativo | L6: Rio Grande | M6: RS | N6: -32.0349 | O6: -52.1071
A7: 6 | B7: Roberta de Cassia | C7: Roberta de Cassia | D7: Roberta De Cássia Martareli | E7: Roberta de Cássia | F7: Roberta de Cássia Martareli | G7: (11) 95337-4199 | H7: roberta.ampm@igtgroup-ext.com.br | I7: Rua lagoa d'anta 60, pq cisper São Paulo, CEP 03818-030 | J7: 291.322.248-00 | K7: Ativo | L7: São Paulo | M7: SP | N7: -23.5329 | O7: -46.6395
A8: 7 | B8: Lucas Silva | C8: Lucas Silva | D8: Lucas Silva Dos Santos | E8: Lucas Silva | F8: Lucas Silva dos Santos | G8: (11) 97707-5141 | H8: lucas.ampm@igtgroup-ext.com.br | I8: Rua Paraíba, 324, Nossa Senhora de Fátima, Monte Carmelo - MG. CEP: 38500-000 | J8: 095.374.106-09 | K8: Ativo | L8: Monte Carlo | M8: MG
A9: 8 | B9: Andre Luiz | C9: Andre Luiz | D9: AndrÃ© Luiz De Medeiros | E9: Andre Luiz | F9: André Luiz de Medeiros | G9: (81) 9386-9032 | H9: andre.ampm@igtgroup-ext.com.br | I9: R SEBASTIAO DO SOUTO 109, CEP 54360-030 | J9: 034.327.224-51 | K9: Saiu
A10: 9 | B10: Diego Henrique | C10: Diego Henrique | D10: Diego Henrique De Souza | E10: Diego Henrique | F10: Diego Henrique de Souza | G10: (41) 8706-3610 | H10: diego.ampm@igtgroup-ext.com.br | I10: aRua florindo Rinaldin n° 92 sobrado 3, CEP 81810-600 | J10: 066.830.679-37 | K10: Saiu
A11: 10 | B11: Juliano Amoretti | C11: Juliano Amoretti | D11: Juliano Rodrigues Amoretti | F11: Juliano Rodrigues Amoretti | G11: (48) 9138-0057 | H11: juliano.ampm@igtgroup-ext.com.br | I11: Rua Campeche 1560 CEP: 88063-300 | J11: 005.050.010-47 | K11: Saiu
A12: 11 | B12: Marcela Lourenço | C12: Marcela Lourenço | D12: Marcela Lourenço Venegas | E12: Marcela Lourenço | F12: Marcela Lourenço | G12: (43) 9159-2334 | H12: marcela.ampm@igtgroup-ext.com.br | I12: Av Joao Miguel Caram, 1075 - BL2 AP 702 ANDAR 8 | J12: 043.614.499-96 | K12: Saiu
A13: 12 | B13: Simone Franceschi | C13: Simone Franceschi | D13: Simone Franceschi Barreto | E13: Simone Franceshi | F13: Simone Franceschi Barreto | G13: (47) 9252-8844 | H13: simone.ampm@igtgroup-ext.com.br | I13: RUA ARNALDO DAVETT 386 BOA ESPINHEIROS, CEP 89228-560 JOINVILLE - SC | J13: 075.811.997-62 | K13: Saiu
A14: 13 | B14: Tabajara Grecca | C14: Tabajara Grecca | D14: Tabajara Grecca | F14: Tabajara Grecca | G14: (19) 98161-1163 | H14: tabajara.ampm@igtgroup-ext.com.br | I14: Av. José Luis Camargo Moreira, 33 ap 42 torre 2 - Mansões Santo Antonio - Campinas/SP - CEP: 13087-511 | J14: 071520578/18 | K14: Saiu

Sheet Treinamentos_Feitos
A1: Data | B1: Instrutor_Unificado | C1: Posto | D1: PV Abadi | E1: Tipo do Treinamento | F1: ValorAjudadeCusto | G1: ValorDiária | H1: Custo_Total_R$ | I1: Cidade | J1: Reginal | K1: ciclo.competencia
A2: 45467 | B2: André Luiz de Medeiros | C2: 120261 - Auto Posto Estradao De Itarare Ltda | D2: 120261 | E2: teste | F2: 105.47 | G2: 238.1 | H2: 495.23 | I2: Rio de Janeiro - RJ | J2: Sudeste | K2: 01/06/2024
A3: 45470 | B3: André Luiz de Medeiros | C3: Sede Igt | E3: teste | F3: 105.47 | G3: 238.1 | H3: 495.23 | I3: Rio de Janeiro - RJ | J3: Sudeste | K3: 01/06/2024
A4: 45490 | B4: William Nunes (NAO CADASTRADO) | C4: 1275371 - Posto Avant Eireli | D4: 1275371 | E4: Treinamento de Loja Café | F4: 105.47 | G4: 238.1 | H4: 495.23 | I4: Canoas - RS | J4: Sul | K4: 01/07/2024
A5: 45491 | B5: William Nunes (NAO CADASTRADO) | C5: 1275371 - Posto Avant Eireli | D5: 1275371 | E5: Treinamento de Loja Café | F5: 105.47 | G5: 238.1 | H5: 495.23 | I5: Canoas - RS | J5: Sul | K5: 01/07/2024
A6: 45492 | B6: William Nunes (NAO CADASTRADO) | C6: 1275371 - Posto Avant Eireli | D6: 1275371 | E6: Treinamento de Loja Café | F6: 105.47 | G6: 238.1 | H6: 495.23 | I6: Canoas - RS | J6: Sul | K6: 01/07/2024
A7: 45495 | B7: William Nunes (NAO CADASTRADO) | C7: 1334528 - Posto Sao Joaquim Eireli | D7: 1334528 | E7: Treinamento de Loja Padaria | F7: 105.47 | G7: 238.1 | H7: 495.23 | I7: Sao Leopoldo - RS | J7: Sul | K7: 01/07/2024
A8: 45496 | B8: William Nunes (NAO CADASTRADO) | C8: 1334528 - Posto Sao Joaquim Eireli | D8: 1334528 | E8: Treinamento de Loja Padaria | F8: 105.47 | G8: 238.1 | H8: 495.23 | I8: Sao Leopoldo - RS | J8: Sul | K8: 01/07/2024
A9: 45497 | B9: William Nunes (NAO CADASTRADO) | C9: 1334528 - Posto Sao Joaquim Eireli | D9: 1334528 | E9: Treinamento de Loja Padaria | F9: 105.47 | G9: 238.1 | H9: 495.23 | I9: Sao Leopoldo - RS | J9: Sul | K9: 01/07/2024
A10: 45498 | B10: Diego Henrique de Souza | C10: 1300414 - Auto Posto Valencia Ltda | D10: 1300414 | E10: Treinamento de 93Burger | F10: 105.47 | G10: 238.1 | H10: 495.23 | I10: Curitiba - PR | J10: Sul | K10: 01/07/2024
A11: 45498 | B11: Diego Henrique de Souza | C11: 1300414 - Auto Posto Valencia Ltda | D11: 1300414 | E11: Treinamento de 93Burger | F11: 0 | G11: 0 | H11: 0 | I11: Curitiba - PR | J11: Sul | K11: 01/07/2024
A12: 45498 | B12: William Nunes (NAO CADASTRADO) | C12: 1334528 - Posto Sao Joaquim Eireli | D12: 1334528 | E12: Treinamento de Loja Padaria | F12: 105.47 | G12: 238.1 | H12: 495.23 | I12: Sao Leopoldo - RS | J12: Sul | K12: 01/07/2024
A13: 45499 | B13: William Nunes (NAO CADASTRADO) | C13: 1334528 - Posto Sao Joaquim Eireli | D13: 1334528 | E13: Treinamento de Loja Padaria | F13: 105.47 | G13: 238.1 | H13: 495.23 | I13: Sao Leopoldo - RS | J13: Sul | K13: 01/07/2024
A14: 45499 | B14: Simone Franceschi Barreto | C14: 101284 - Patio Contorno Comercio De Combustiveis | D14: 101284 | E14: Treinamento de 93Burger | F14: 105.47 | G14: 0 | H14: 152.02 | I14: Curitiba - PR | J14: Sul | K14: 01/07/2024
A15: 45510 | B15: André Luiz de Medeiros | C15: 1365924 - Posto 4 Rodas Eireli | D15: 1365924 | E15: Treinamento de Loja Café | F15: 105.47 | G15: 238.1 | H15: 495.23 | I15: São Miguel dos Campos - AL | J15: Nordeste | K15: 01/08/2024
... A29: 45518 | B29: Lucas Silva dos Santos | C29: 1305137 - Rede Dol Comercio De Combustiveis Ltda | D29: 1305137 | E29: Treinamento de Loja Café | F29: 105.47 | G29: 238.1 | H29: 495.23 | I29: Uberlândia - MG | J29: Sudeste | K29: 01/08/2024
A30: 45518 | B30: Simone Franceschi Barreto | C30: Treinamento Online | E30: Implantação | F30: 105.47 | G30: 0 | H30: 152.02 | I30: Online | J30: Norte | K30: 01/08/2024
A31: 45518 | B31: Simone Franceschi Barreto | C31: Treinamento Online | E31: Implantação | F31: 0 | G31: 0 | H31: 0 | I31: Online | J31: Norte | K31: 01/08/2024
A32: 45519 | B32: Diego Henrique de Souza | C32: 1305012 - Chr Comercio De Combustiveis Ltda | D32: 1305012 | E32: Treinamento de Loja Padaria | F32: 105.47 | G32: 238.1 | H32: 495.23 | I32: Maringa - PR | J32: Sul | K32: 01/08/2024
A33: 45519 | B33: Lucas Silva dos Santos | C33: 1305137 - Rede Dol Comercio De Combustiveis Ltda | D33: 1305137 | E33: Treinamento de Loja Café | F33: 105.47 | G33: 238.1 | H33: 495.23 | I33: Uberlândia - MG | J33: Sudeste | K33: 01/08/2024
A34: 45519 | B34: Simone Franceschi Barreto | C34: Treinamento Online | E34: Implantação | F34: 105.47 | G34: 0 | H34: 152.02 | I34: Online | J34: Norte | K34: 01/08/2024
A35: 45520 | B35: Simone Franceschi Barreto | C35: Treinamento Online | E35: Implantação | F35: 0 | G35: 0 | H35: 0 | I35: Online | J35: Norte | K35: 01/08/2024
A36: 45520 | B36: Simone Franceschi Barreto | C36: Treinamento Online | E36: Implantação | F36: 0 | G36: 0 | H36: 0 | I36: Online | J36: Norte | K36: 01/08/2024
A37: 45520 | B37: Simone Franceschi Barreto | C37: Treinamento Online | E37: Implantação | F37: 0 | G37: 0 | H37: 0 | I37: Online | J37: Norte | K37: 01/08/2024
A38: 45520 | B38: Simone Franceschi Barreto | C38: Treinamento Online | E38: Implantação | F38: 105.47 | G38: 0 | H38: 152.02 | I38: Online | J38: Norte | K38: 01/08/2024
A39: 45520 | B39: Diego Henrique de Souza | C39: 1305012 - Chr Comercio De Combustiveis Ltda | D39: 1305012 | E39: Treinamento de Loja Padaria | F39: 105.47 | G39: 238.1 | H39: 495.23 | I39: Maringa - PR | J39: Sul | K39: 01/08/2024
A40: 45523 | B40: Simone Franceschi Barreto | C40: Treinamento Online | E40: Treinamento de Loja Padaria | F40: 105.47 | G40: 0 | H40: 152.02 | I40: Curitiba - PR | J40: Sul | K40: 01/08/2024
A41: 45523 | B41: William Nunes (NAO CADASTRADO) | C41: 1275508 - Posto De Combustiveis Caminho Do Gol Lt | D41: 1275508 | E41: Implantação | F41: 105.47 | G41: 238.1 | H41: 495.23 | I41: Taquara - RS | J41: Sul | K41: 01/08/2024
A42: 45524 | B42: Lucas Silva dos Santos | C42: 1335388 - Posto Jardim Veneza Ltda | D42: 1335388 | E42: Implantação | F42: 105.47 | G42: 238.1 | H42: 495.23 | I42: Uberlândia -MG - 10 | J42: Norte | K42: 01/08/2024
A43: 45524 | B43: Simone Franceschi Barreto | C43: Treinamento Online | E43: Treinamento de Loja Padaria | F43: 105.47 | G43: 0 | H43: 152.02 | I43: Curitiba - PR | J43: Sul | K43: 01/08/2024
A44: 45524 | B44: William Nunes (NAO CADASTRADO) | C44: 1275508 - Posto De Combustiveis Caminho Do Gol Lt | D44: 1275508 | E44: Inauguração | F44: 105.47 | G44: 238.1 | H44: 495.23 | I44: Porto Alegre - RS | J44: Sul | K44: 01/08/2024
A45: 45525 | B45: Lucas Silva dos Santos | C45: 1304905 - Ursa Maior Derivados De Petroleo Ltda | D45: 1304905 | E45: Implantação | F45: 105.47 | G45: 238.1 | H45: 495.23 | I45: Uberlândia - MG | J45: Sudeste | K45: 01/08/2024
A46: 45525 | B46: Lucas Silva dos Santos | C46: 1304905 - Ursa Maior Derivados De Petroleo Ltda | D46: 1304905 | E46: Implantação | F46: 0 | G46: 0 | H46: 0 | I46: Uberlandia - MG | J46: Sudeste | K46: 01/08/2024
A47: 45525 | B47: Simone Franceschi Barreto | C47: Treinamento Online | E47: Treinamento de Loja Padaria | F47: 105.47 | G47: 0 | H47: 152.02 | I47: Curitiba - PR | J47: Sul | K47: 01/08/2024
A48: 45525 | B48: William Nunes (NAO CADASTRADO) | C48: 1275508 - Posto De Combustiveis Caminho Do Gol Lt | D48: 1275508 | E48: Inauguração | F48: 105.47 | G48: 238.1 | H48: 495.23 | I48: Porto Alegre - RS | J48: Sul | K48: 01/08/2024
A49: 45526 | B49: William Nunes (NAO CADASTRADO) | C49: 1275508 - Posto De Combustiveis Caminho Do Gol Lt | D49: 1275508 | E49: Inauguração | F49: 105.47 | G49: 238.1 | H49: 495.23 | I49: Porto Alegre - RS | J49: Sul | K49: 01/08/2024
A50: 45526 | B50: Simone Franceschi Barreto | C50: Treinamento Online | E50: Treinamento de Loja Padaria | F50: 105.47 | G50: 0 | H50: 152.02 | I50: Curitiba - PR | J50: Sul | K50: 01/08/2024
A51: 45526 | B51: Lucas Silva dos Santos | C51: 1348992 - Auto Posto Morada Ltda | D51: 1348992 | E51: Implantação | F51: 0 | G51: 0 | H51: 0 | I51: Uberaba - MG | J51: Sudeste | K51: 01/08/2024
A52: 45526 | B52: Lucas Silva dos Santos | C52: 1404999 - Rede Super S 2.0 Ltda | D52: 1404999 | E52: Implantação | F52: 105.47 | G52: 238.1 | H52: 495.23 | I52: Uberaba - MG | J52: Sudeste | K52: 01/08/2024
A53: 45527 | B53: Lucas Silva dos Santos | C53: 1372737 - Abastecedora Fenix Ltda | D53: 1372737 | E53: Implantação | F53: 105.47 | G53: 238.1 | H53: 495.23 | I53: Uberaba - MG | J53: Sudeste | K53: 01/08/2024
A54: 45527 | B54: Simone Franceschi Barreto | C54: Treinamento Online | E54: Treinamento de Loja Padaria | F54: 105.47 | G54: 0 | H54: 152.02 | I54: Curitiba - PR | J54: Sul | K54: 01/08/2024
A55: 45527 | B55: William Nunes (NAO CADASTRADO) | C55: 1275508 - Posto De Combustiveis Caminho Do Gol Lt | D55: 1275508 | E55: Inauguração | F55: 105.47 | G55: 238.1 | H55: 495.23 | I55: Porto Alegre - RS | J55: Sul | K55: 01/08/2024
A56: 45528 | B56: William Nunes (NAO CADASTRADO) | C56: 1275508 - Posto De Combustiveis Caminho Do Gol Lt | D56: 1275508 | E56: Inauguração | F56: 105.47 | G56: 238.1 | H56: 495.23 | I56: Porto Alegre - RS | J56: Sul | K56: 01/08/2024
A57: 45530 | B57: William Nunes (NAO CADASTRADO) | C57: 1275508 - Posto De Combustiveis Caminho Do Gol Lt | D57: 1275508 | E57: Inauguração | F57: 105.47 | G57: 238.1 | H57: 495.23 | I57: Porto Alegre - RS | J57: Sul | K57: 01/08/2024
A58: 45530 | B58: Simone Franceschi Barreto | C58: Treinamento Online | E58: Treinamento Online AmPm | F58: 0 | G58: 0 | H58: 0 | I58: Online | J58: Norte | K58: 01/08/2024
A59: 45530 | B59: Marcela Lourenço | C59: Treinamento Online | E59: Treinamento Online AmPm | F59: 0 | G59: 0 | H59: 0 | I59: Online | J59: Norte | K59: 01/08/2024
A60: 45530 | B60: Simone Franceschi Barreto | C60: Treinamento Online | E60: Treinamento Online AmPm | F60: 105.47 | G60: 0 | H60: 152.02 | I60: Online | J60: Norte | K60: 01/08/2024
A61: 45530 | B61: Lucas Silva dos Santos | C61: 1368133 - Camargo Combustiveis Ltda - Me | D61: 1368133 | E61: Treinamento de Loja Padaria | F61: 105.47 | G61: 238.1 | H61: 495.23 | I61: Araxa - MG | J61: Sudeste | K61: 01/08/2024
A62: 45530 | B62: Diego Henrique de Souza | C62: 1360825 - Auto Posto Mirante De Ourinhos Ltda | D62: 1360825 | E62: Repasse de Op. | F62: 105.47 | G62: 238.1 | H62: 495.23 | I62: Ourinhos - SP | J62: Sudeste | K62: 01/08/2024
A63: 45530 | B63: André Luiz de Medeiros | C63: 1401066 - Posto Qualas Ltda | D63: 1401066 | E63: Treinamento de Loja Padaria + 93 Burger | F63: 52.74 | G63: 119.05 | H63: 247.63 | I63: Limeira - SP | J63: Sudeste | K63: 01/08/2024
A64: 45530 | B64: Marcela Lourenço | C64: Treinamento Online | E64: Treinamento Online AmPm | F64: 105.47 | G64: 238.1 | H64: 495.23 | I64: Online | J64: Norte | K64: 01/08/2024
A65: 45531 | B65: André Luiz de Medeiros | C65: 1401066 - Posto Qualas Ltda | D65: 1401066 | E65: Treinamento de Loja Padaria + 93 Burger | F65: 52.74 | G65: 119.05 | H65: 247.63 | I65: Limeira - SP | J65: Sudeste | K65: 01/08/2024
A66: 45531 | B66: Diego Henrique de Souza | C66: 1360825 - Auto Posto Mirante De Ourinhos Ltda | D66: 1360825 | E66: Repasse de Op. | F66: 105.47 | G66: 238.1 | H66: 495.23 | I66: Ourinhos - SP | J66: Sudeste | K66: 01/08/2024
A67: 45531 | B67: Lucas Silva dos Santos | C67: 1368133 - Camargo Combustiveis Ltda - Me | D67: 1368133 | E67: Treinamento de Loja Padaria | F67: 105.47 | G67: 238.1 | H67: 495.23 | I67: Araxa - MG | J67: Sudeste | K67: 01/08/2024
A68: 45531 | B68: Marcela Lourenço | C68: Treinamento Online | E68: Treinamento Online AmPm | F68: 105.47 | G68: 238.1 | H68: 495.23 | I68: Online | J68: Norte | K68: 01/08/2024
A69: 45531 | B69: Simone Franceschi Barreto | C69: Treinamento Online | E69: Treinamento Online AmPm | F69: 105.47 | G69: 0 | H69: 152.02 | I69: Online | J69: Norte | K69: 01/08/2024
A70: 45531 | B70: William Nunes (NAO CADASTRADO) | C70: 614998 - Rede Farroupilha Gestao, Varejo E Inova | D70: 614998 | E70: Inauguração | F70: 105.47 | G70: 238.1 | H70: 495.23 | I70: Canoas - RS | J70: Sul | K70: 01/08/2024
A71: 45532 | B71: William Nunes (NAO CADASTRADO) | C71: 614998 - Rede Farroupilha Gestao, Varejo E Inova | D71: 614998 | E71: Inauguração | F71: 105.47 | G71: 238.1 | H71: 495.23 | I71: Canoas - RS | J71: Sul | K71: 01/08/2024
A72: 45532 | B72: Marcela Lourenço | C72: Treinamento Online | E72: Treinamento Online AmPm | F72: 105.47 | G72: 238.1 | H72: 495.23 | I72: Online | J72: Norte | K72: 01/08/2024
A73: 45532 | B73: Simone Franceschi Barreto | C73: Treinamento Online | E73: Treinamento de Mr. Cheney | F73: 105.47 | G73: 0 | H73: 152.02 | I73: Online | J73: Norte | K73: 01/08/2024
A74: 45532 | B74: Diego Henrique de Souza | C74: 1360825 - Auto Posto Mirante De Ourinhos Ltda | D74: 1360825 | E74: Repasse de Op. | F74: 105.47 | G74: 238.1 | H74: 495.23 | I74: Ourinhos - SP | J74: Sudeste | K74: 01/08/2024
A75: 45532 | B75: André Luiz de Medeiros | C75: 1401066 - Posto Qualas Ltda | D75: 1401066 | E75: Treinamento de Loja Padaria + 93 Burger | F75: 52.74 | G75: 119.05 | H75: 247.63 | I75: Limeira - SP | J75: Sudeste | K75: 01/08/2024
A76: 45532 | B76: Lucas Silva dos Santos | C76: 1305137 - Rede Dol Comercio De Combustiveis Ltda | D76: 1305137 | E76: Treinamento de Loja Padaria | F76: 105.47 | G76: 238.1 | H76: 495.23 | I76: Uberlândia - MG | J76: Sudeste | K76: 01/08/2024
A77: 45533 | B77: André Luiz de Medeiros | C77: 1401066 - Posto Qualas Ltda | D77: 1401066 | E77: Treinamento de Loja Padaria + 93 Burger | F77: 52.74 | G77: 119.05 | H77: 247.63 | I77: Limeira - SP | J77: Sudeste | K77: 01/08/2024
A78: 45533 | B78: Diego Henrique de Souza | C78: 1360825 - Auto Posto Mirante De Ourinhos Ltda | D78: 1360825 | E78: Repasse de Op. | F78: 105.47 | G78: 238.1 | H78: 495.23 | I78: Ourinhos - SP | J78: Sudeste | K78: 01/08/2024
A79: 45533 | B79: Lucas Silva dos Santos | C79: 1305137 - Rede Dol Comercio De Combustiveis Ltda | D79: 1305137 | E79: Treinamento de Loja Padaria | F79: 105.47 | G79: 238.1 | H79: 495.23 | I79: Uberlândia - MG | J79: Sudeste | K79: 01/08/2024
A80: 45533 | B80: Simone Franceschi Barreto | C80: Treinamento Online | E80: Implantação | F80: 105.47 | G80: 0 | H80: 152.02 | I80: Online | J80: Norte | K80: 01/08/2024
A81: 45533 | B81: Simone Franceschi Barreto | C81: Treinamento Online | E81: Implantação | F81: 0 | G81: 0 | H81: 0 | I81: Online | J81: Norte | K81: 01/08/2024
A82: 45533 | B82: Simone Franceschi Barreto | C82: Treinamento Online | E82: Implantação | F82: 0 | G82: 0 | H82: 0 | I82: Online | J82: Norte | K82: 01/08/2024
A83: 45533 | B83: William Nunes (NAO CADASTRADO) | C83: 614998 - Rede Farroupilha Gestao, Varejo E Inova | D83: 614998 | E83: Inauguração | F83: 105.47 | G83: 238.1 | H83: 495.23 | I83: Canoas - RS | J83: Sul | K83: 01/08/2024
A84: 45534 | B84: André Luiz de Medeiros | C84: 1401066 - Posto Qualas Ltda | D84: 1401066 | E84: Treinamento de Loja Padaria + 93 Burger | F84: 52.74 | G84: 119.05 | H84: 247.63 | I84: Limeira - SP | J84: Sudeste | K84: 01/08/2024
A85: 45534 | B85: Diego Henrique de Souza | C85: 1360825 - Auto Posto Mirante De Ourinhos Ltda | D85: 1360825 | E85: Repasse de Op. | F85: 105.47 | G85: 238.1 | H85: 495.23 | I85: Ourinhos - SP | J85: Sudeste | K85: 01/08/2024
A86: 45537 | B86: Roberta de Cássia Martareli | C86: 1340510 - Posto De Gasolina Monte Carlo Ltda | D86: 1340510 | E86: Retrofit | F86: 105.47 | G86: 238.1 | H86: 495.23 | I86: Santo Andre - SP | J86: Sudeste | K86: 01/09/2024
A87: 45537 | B87: Lucas Silva dos Santos | C87: 112231 - Rede Super S 2.0 Ltda | D87: 112231 | E87: Inauguração | F87: 105.47 | G87: 238.1 | H87: 495.23 | I87: Uberaba - MG - 529 | J87: Norte | K87: 01/09/2024
A88: 45538 | B88: Lucas Silva dos Santos | C88: 112231 - Rede Super S 2.0 Ltda | D88: 112231 | E88: Inauguração | F88: 105.47 | G88: 238.1 | H88: 495.23 | I88: Uberaba - MG - 529 | J88: Norte | K88: 01/09/2024
A89: 45538 | B89: Roberta de Cássia Martareli | C89: 1340510 - Posto De Gasolina Monte Carlo Ltda | D89: 1340510 | E89: Retrofit | F89: 105.47 | G89: 238.1 | H89: 495.23 | I89: Santo Andre - SP | J89: Sudeste | K89: 01/09/2024
A90: 45538 | B90: William Nunes (NAO CADASTRADO) | C90: 616508 - Posto De Combustiveis Brock E Cifra Ltd | D90: 616508 | E90: Implantação | F90: 105.47 | G90: 238.1 | H90: 495.23 | I90: Passo Fundo - RS | J90: Sul | K90: 01/09/2024
A91: 45539 | B91: Diego Henrique de Souza | C91: 620633 - California Automotivos Ltda | D91: 620633 | E91: Implantação | F91: 52.74 | G91: 119.05 | H91: 247.63 | I91: Califórnia - PR | J91: Sul | K91: 01/09/2024
A92: 45539 | B92: André Luiz de Medeiros | C92: 709048 - Beluma Comercio De Combustiveis Ltda | D92: 709048 | E92: Inauguração | F92: 105.47 | G92: 238.1 | H92: 495.23 | I92: Maceió - AL | J92: Nordeste | K92: 01/09/2024
A93: 45539 | B93: Diego Henrique de Souza | C93: 685698 - Auto Posto Palestra Ltda | D93: 685698 | E93: Implantação | F93: 0 | G93: 0 | H93: 0 | I93: Iguaraçu - PR | J93: Sul | K93: 01/09/2024
A94: 45539 | B94: Lucas Silva dos Santos | C94: 112231 - Rede Super S 2.0 Ltda | D94: 112231 | E94: Inauguração | F94: 105.47 | G94: 238.1 | H94: 495.23 | I94: Uberaba - MG - 529 | J94: Norte | K94: 01/09/2024
A95: 45539 | B95: Roberta de Cássia Martareli | C95: 1340510 - Posto De Gasolina Monte Carlo Ltda | D95: 1340510 | E95: Retrofit | F95: 105.47 | G95: 238.1 | H95: 495.23 | I95: Santo Andre - SP | J95: Sudeste | K95: 01/09/2024
A96: 45539 | B96: Simone Franceschi Barreto | C96: Treinamento Online | E96: Implantação | F96: 105.47 | G96: 0 | H96: 152.02 | I96: Online | J96: Norte | K96: 01/09/2024
A97: 45540 | B97: William Nunes (NAO CADASTRADO) | C97: 614197 - Benetti Comercial De Combustiveis Ltda - 1 | D97: 614197 | E97: Implantação | F97: 105.47 | G97: 238.1 | H97: 495.23 | I97: Gramado - RS | J97: Sul | K97: 01/09/2024
A98: 45540 | B98: Simone Franceschi Barreto | C98: Treinamento Online | E98: Implantação | F98: 105.47 | G98: 0 | H98: 152.02 | I98: Online | J98: Norte | K98: 01/09/2024
A99: 45540 | B99: Roberta de Cássia Martareli | C99: 1340510 - Posto De Gasolina Monte Carlo Ltda | D99: 1340510 | E99: Retrofit | F99: 105.47 | G99: 238.1 | H99: 495.23 | I99: Santo Andre - SP | J99: Sudeste | K99: 01/09/2024
A100: 45540 | B100: Marcela Lourenço | C100: 22771 - Tangara Comercio De Combustiveis Ltda | D100: 22771 | E100: Treinamento de 93 Burger | F100: 0 | G100: 0 | H100: 0 | I100: Maringá - PR | J100: Sul | K100: 01/09/2024
A101: 45540 | B101: Diego Henrique de Souza | C101: 22771 - Tangara Comercio De Combustiveis Ltda | D101: 22771 | E101: Implantação | F101: 0 | G101: 0 | H101: 0 | I101: Maringá - PR | J101: Sul | K101: 01/09/2024
A102: 45540 | B102: Diego Henrique de Souza | C102: 620717 - Posto Oasis Ltda | D102: 620717 | E102: Implantação | F102: 105.47 | G102: 238.1 | H102: 495.23 | I102: Maringá - PR | J102: Sul | K102: 01/09/2024
A103: 45540 | B103: André Luiz de Medeiros | C103: 709048 - Beluma Comercio De Combustiveis Ltda | D103: 709048 | E103: Inauguração | F103: 105.47 | G103: 238.1 | H103: 495.23 | I103: Maceió - AL | J103: Nordeste | K103: 01/09/2024
A104: 45540 | B104: Marcela Lourenço | C104: 620717 - Posto Oasis Ltda | D104: 620717 | E104: Treinamento de 93 Burger | F104: 105.47 | G104: 238.1 | H104: 495.23 | I104: Maringá - PR | J104: Sul | K104: 01/09/2024
A105: 45541 | B105: André Luiz de Medeiros | C105: 709048 - Beluma Comercio De Combustiveis Ltda | D105: 709048 | E105: Inauguração | F105: 105.47 | G105: 238.1 | H105: 495.23 | I105: Maceió - AL | J105: Nordeste | K105: 01/09/2024
A106: 45541 | B106: Roberta de Cássia Martareli | C106: 1340510 - Posto De Gasolina Monte Carlo Ltda | D106: 1340510 | E106: Retrofit | F106: 105.47 | G106: 238.1 | H106: 495.23 | I106: Santo Andre - SP | J106: Sudeste | K106: 01/09/2024
A107: 45541 | B107: William Nunes (NAO CADASTRADO) | C107: 618949 - Comercial De Combs Caminho Verde Ltda | D107: 618949 | E107: Implantação | F107: 105.47 | G107: 238.1 | H107: 495.23 | I107: Porto Alegre - RS | J107: Sul | K107: 01/09/2024
A108: 45544 | B108: William Nunes (NAO CADASTRADO) | C108: 1338094 - Posto Imperial Ltda | D108: 1338094 | E108: Repasse de Op. | F108: 105.47 | G108: 238.1 | H108: 495.23 | I108: Campo Grande - MS | J108: Centro-Oeste | K108: 01/09/2024
A109: 45544 | B109: Diego Henrique de Souza | C109: 200889 - Rede Furnas Comercio Combustiveis Ltda | D109: 200889 | E109: Migração | F109: 105.47 | G109: 238.1 | H109: 495.23 | I109: Tubarão - SC | J109: Sul | K109: 01/09/2024
A110: 45544 | B110: Roberta de Cássia Martareli | C110: 678596 - Centro Automotivo Himalaia Ltda | D110: 678596 | E110: Inauguração | F110: 105.47 | G110: 238.1 | H110: 495.23 | I110: Jd. Angela - Zo | J110: Norte | K110: 01/09/2024
... A342: 45595 | B342: Simone Franceschi Barreto | C342: 1340191 - Posto Galo Ltda | D342: 1340191 | E342: Inauguração + Implantação | F342: 105.47 | G342: 0 | H342: 152.02 | I342: Palhoça - SC | J342: Sul | K342: 01/10/2024
A343: 45595 | B343: Roberta de Cássia Martareli | C343: Caravela Conveniência Santa Tereza | E343: Inauguração | F343: 105.47 | G343: 238.1 | H343: 495.23 | I343: Carapicuíba - SP | J343: Sudeste | K343: 01/10/2024
A344: 45595 | B344: Marcela Lourenço | C344: 616922 - Posto De Combustivel Alegria Ltda | D344: 616922 | E344: Repasse de Op | F344: 105.47 | G344: 238.1 | H344: 495.23 | I344: Resende - RJ | J344: Sudeste | K344: 01/10/2024
...

Sheet Rede_de_Lojas
A1: PV Abadi | B1: Razão Social | C1: Status Loja | D1: Municipio | E1: UF | F1: Endereço | G1: CEP | H1: Data Inauguracao | I1: Modelo Loja Gerencial | J1: GF | K1: CF | L1: Latitude | M1: Longitude
A2: 404622 | B2: Jl Lemos Combustivel Ltda | C2: Ativo | D2: Jaboatao Dos Guararapes | E2: PE | F2: Av Ayrton Senna Da Silva 3300 | G2: 54410240 | H2: 44124 | I2: Ampm Padaria Compacta 2020 | J2: GF N/NE | K2: Caroline De Figueiredo Cavalcanti Albuquerque | L2: -8.11298 | M2: -35.015
A3: 613879 | B3: Auto Posto Ferrari Ltda | C3: Ativo | D3: Porto Alegre | E3: RS | F3: Av Juca Batista 4329 | G3: 91755000 | H3: 38376 | I3: Loja Ampm 2020 | J3: GF RS | K3: Karine Silveira Boardmann | L3: -30.0318 | M3: -51.2065
A4: 4230 | B4: C A Olimpia Bandeirantes Ltda | C4: Ativo | D4: Sao Paulo | E4: SP | F4: R Bugio, 79 | G4: 4548070 | H4: 35551 | I4: Ampm Padaria Compacta Fachada 2025 | J4: GF SP Capital | K4: Peterson Da Silva Conceicao | L4: -23.5329 | M4: -46.6395
A5: 613886 | B5: Abastecedora De Combustiveis Neiva Ltda | C5: Ativo | D5: Porto Alegre | E5: RS | F5: Av Wenceslau Escobar 2226 | G5: 91900000 | H5: 45139 | I5: Ampm Padaria Compacta 2020 | J5: GF RS | K5: Karine Silveira Boardmann | L5: -30.0318 | M5: -51.2065
A6: 12632 | B6: Jli Combustivel Ltda | C6: Ativo | D6: Jaboatao Dos Guararapes | E6: PE | F6: R Aniceto Varejao 530 | G6: 54420310 | H6: 43056 | I6: Ampm Padaria Compacta 2020 | J6: GF N/NE | K6: Caroline De Figueiredo Cavalcanti Albuquerque | L6: -8.11298 | M6: -35.015
A7: 619761 | B7: Gdo Participacoes S/A | C7: Ativo | D7: Sao Paulo | E7: SP | F7: Av Dos Bandeirantes 3686 | G7: 4071000 | H7: 37165 | I7: Ampm Padaria Compacta 2020 | J7: GF SP Capital | K7: Flavio Pereira De Almeida | L7: -23.5329 | M7: -46.6395
A8: 4194 | B8: Posto Uni Icaray Ltda | C8: Ativo | D8: Aracatuba | E8: SP | F8: Av Joaquim Pompeu De Toledo 1631 | G8: 16020105 | H8: 35643 | I8: Loja Ampm | J8: GF SP Interior | K8: Thais Viana Silva | L8: -21.2076 | M8: -50.4401
A9: 620584 | B9: Posto Uni Paulistinha Ltda | C9: Ativo | D9: Presidente Prudente | E9: SP | F9: Av Washington Luiz 1067 | G9: 19015150 | H9: 42706 | I9: Ampm Padaria Compacta 2025 | J9: GF SP Interior | K9: Thais Viana Silva | L9: -22.1207 | M9: -51.3925
A10: 621129 | B10: Edilma De Oli Lac Siqueira Campos Me | C10: Ativo | D10: Sertania | E10: PE | F10: Av Cicero Lacerda 48 | G10: 56600000 | H10: 40908 | I10: Loja Ampm Fachada 2020 | J10: GF N/NE | K10: Caroline De Figueiredo Cavalcanti Albuquerque | L10: -8.06847 | M10: -37.2684
A11: 11095 | B11: Dist Way De Combs Ltda | C11: Ativo | D11: Rio De Janeiro | E11: RJ | F11: Av Das Americas 2100 | G11: 22640101 | H11: 38169 | I11: Ampm Padaria Full 2020 | J11: GF Sudeste | K11: Andre Luiz Nogueira Mantuano | L11: -22.9129 | M11: -43.2003
A12: 621267 | B12: Posto Monteiro Ltda | C12: Ativo | D12: Cabo De Santo Agostinho | E12: PE | F12: Rod Pe 60 Sn Km 08 | G12: 54520992 | H12: 41313 | I12: Loja Ampm 2025 | J12: GF N/NE | K12: Caroline De Figueiredo Cavalcanti Albuquerque | L12: -8.28218 | M12: -35.0253
A13: 13252 | B13: Posto Barra Linda Ltda | C13: Ativo | D13: Rio De Janeiro | E13: RJ | F13: Av Das Americas 7000 | G13: 22793081 | H13: 35827 | I13: Ampm Padaria Full Fachada 2020 | J13: GF Sudeste | K13: Andre Luiz Nogueira Mantuano | L13: -22.9129 | M13: -43.2003
... A222: 22231 | B222: Auto Posto Casil Ltda | C222: Ativo | D222: Sao Jose Dos Pinhais | E222: PR | F222: R Tenente Djalma Dutra 125 | G222: 83005360 | H222: 36130 | I222: Ampm Padaria Full 2025 | J222: GF PR | K222: Jheniffer Guimaraes Catafesta | L222: -25.5313 | M222: -49.2031
A223: 2959 | B223: Cruzada Da Barra Padaria Ltda | C223: Ativo | D223: Rio De Janeiro | E223: RJ | F223: Av Das Americas 3201 Lt 1 Qd 1 | H223: 34121 | I223: Ampm Padaria Full 2020 | J223: GF Sudeste | K223: Andre Luiz Nogueira Mantuano | L223: -22.9129 | M223: -43.2003
A224: 22386 | B224: Posto Barra Norte Ltda | C224: Ativo | D224: Balneario Camboriu | E224: SC | F224: Av Brasil, 220 | G224: 88330040 | H224: 35462 | I224: Ampm Padaria Full | J224: GF SC | K224: Hallmes Dos Santos Oliveira | L224: -26.9926 | M224: -48.6352
A225: 401031 | B225: P De Serv Dengoso Ltda | C225: Ativo | D225: Rio De Janeiro | E225: RJ | F225: Est Do Monteiro, 50 | G225: 23045830 | H225: 41513 | I225: Loja Ampm | J225: GF Sudeste | K225: Andre Luiz Nogueira Mantuano | L225: -22.9129 | M225: -43.2003
A226: 22531 | B226: A P Prudente - Portico Ltda | C226: Ativo | D226: Joinville | E226: SC | F226: R 15 De Novembro 4380 | G226: 89216202 | H226: 35977 | I226: Loja Ampm | J226: GF SC | K226: Tais Da Costa Albano | L226: -26.3045 | M226: -48.8487
A227: 10336 | B227: Via Gas Posto De Servicos Ltda | C227: Ativo | D227: Itaborai | E227: RJ | F227: Av 22 De Maio Sn Lote 01 Quadra 88 | G227: 24800001 | H227: 42675 | I227: Loja Ampm Fachada 2025 | J227: GF Sudeste | K227: Andre Luiz Nogueira Mantuano | L227: -22.7565 | M227: -42.8639
A228: 22629 | B228: Auto Posto Afonso Pena Ltda | C228: Ativo | D228: Curitiba | E228: PR | F228: R Treze De Maio 260 | G228: 80020270 | H228: 44862 | I228: Ampm Padaria Compacta 2025 | J228: GF PR | K228: Jheniffer Guimaraes Catafesta | L228: -25.4195 | M228: -49.2646
A229: 406999 | B229: P Rio Dos Meros Ltda | C229: Ativo | D229: Paraty | E229: RJ | F229: Av Roberto Silveira Sn Qd B Lt 1 | G229: 23970000 | H229: 45649 | I229: Ampm Padaria Compacta Fachada 2025 | J229: GF Sudeste | K229: Andre Luiz Nogueira Mantuano | L229: -23.2221 | M229: -44.7175
A230: 22725 | B230: Auto Posto Principal Ltda | C230: Ativo | D230: Araucaria | E230: PR | F230: Av Doutor Victor Do Amaral 1080 | G230: 83702040 | H230: 38261 | I230: Ampm Padaria Compacta Fachada 2025 | J230: GF PR | K230: Nathalie Voigt | L230: -25.5859 | M230: -49.4047
A231: 23405 | B231: Posto Jotaka Comercio De Combs Ltda | C231: Ativo | D231: Maringa | E231: PR | F231: Av Sao Paulo 2471 Loja 01 | G231: 87005040 | H231: 35827 | I231: Ampm Padaria Compacta 2020 | J231: GF PR | K231: Diego Henrique De Souza | L231: -23.4205 | M231: -51.9333
A232: 402112 | B232: Auto Posto Esal Ltda | C232: Ativo | D232: Angra Dos Reis | E232: RJ | F232: R Almte Machado Portella 179 | G232: 23906190 | H232: 45638 | I232: Ampm Padaria Full 2025 | J232: GF Sudeste | K232: Andre Luiz Nogueira Mantuano | L232: -23.0011 | M232: -44.3196
A233: 23417 | B233: A P Ortona Ltda | C233: Ativo | D233: Curitiba | E233: PR | F233: R Alberto Folloni 1181 | G233: 80540000 | H233: 43829 | I233: Loja Ampm 2025 | J233: GF PR | K233: Wilds Willians Ozanski Campos | L233: -25.4195 | M233: -49.2646
A234: 102066 | B234: Distribuidora Penna Ltda | C234: Ativo | D234: Uberlandia | E234: MG | F234: Av Comendador Alexandrino Garcia 1175 | G234: 38402228 | H234: 36831 | I234: Loja Ampm 2025 | J234: GF Sudeste | K234: Antoniele Meneses Sa | L234: -18.9141 | M234: -48.2749
A235: 14564 | B235: Conveniencia Petroleum Ltda | C235: Ativo | D235: Sao Jose Do Rio Preto | E235: SP | F235: Av Bady Bassitt 4154 | G235: 15025000 | H235: 36161 | I235: Ampm Padaria Full 2020 | J235: GF SP Interior | K235: Bianca Garcia Panchame Da Silveira | L235: -20.8113 | M235: -49.3758
... A292: 613651 | B292: Posto Linha Verde Ltda | C292: Ativo | D292: Viamao | E292: RS | F292: Av Senador Salgado Filho 7277 | G292: 94435000 | H292: 35103 | I292: Ampm Padaria Full 2025 | J292: GF RS | K292: Karine Silveira Boardmann | L292: -30.0819 | M292: -51.0194
A293: 613743 | B293: Abastecedora De Combustiveis Rotula 030 | C293: Ativo | E293: RS | H293: 46203 | I293: Loja Ampm | J293: GF RS | K293: Deborah Evelyn Oliveira
A294: 613884 | B294: Shopping Coml Abast Pr Pet C S Ltda | C294: Ativo | D294: Porto Alegre | E294: RS | F294: Av Joao Wallig 1903 | G294: 91340001 | H294: 35886 | I294: Ampm Padaria Compacta 2020 | J294: GF RS | K294: Marcelo De Abreu Sager | L294: -30.0318 | M294: -51.2065
A295: 620249 | B295: Expresso Conveniencia Lanchonete & Merc | C295: Ativo | D295: Uberaba | E295: MG | F295: Av Nene Sabino 1167 | G295: 38055500 | H295: 44711 | I295: Loja Ampm 2020 | J295: GF Sudeste | K295: Antoniele Meneses Sa | L295: -19.7472 | M295: -47.9381
A296: 613847 | B296: Gbi Combustiveis Ltda | C296: Ativo | D296: Rio Grande | E296: RS | F296: R General Neto 555 | G296: 96200010 | H296: 45461 | I296: Ampm Padaria Compacta 2020 | J296: GF RS | K296: Ruann Goulart Tadiello | L296: -32.0349 | M296: -52.1071
A297: 632730 | B297: Expres Conveni Lanch & Merc Joao Naves | C297: Ativo | D297: Uberlandia | E297: MG | F297: Av Joao Naves De Avila 2735 | G297: 38408144 | H297: 44795 | I297: Loja Ampm 2020 | J297: GF Sudeste | K297: Antoniele Meneses Sa | L297: -18.9141 | M297: -48.2749
A298: 613683 | B298: Auto Posto Felipao Ltda | C298: Ativo | D298: Santa Maria | E298: RS | F298: Av Angelo Bolsson 846 | G298: 97070000 | H298: 36130 | I298: Loja Ampm 2025 | J298: GF RS | K298: Filipe Almeida Candido Da Silva | L298: -29.6868 | M298: -53.8149
A299: 613754 | B299: Mp Postos E Logistica Ltda | C299: Ativo | D299: Santa Maria | E299: RS | F299: Av Presidente Vargas 1079 | G299: 97015511 | H299: 35916 | I299: Loja Ampm | J299: GF RS | K299: Filipe Almeida Candido Da Silva | L299: -29.6868 | M299: -53.8149
A300: 601535 | B300: Posto Linha Verde Ltda | C300: Ativo | D300: Porto Alegre | E300: RS | F300: Av Farrapos 858 | G300: 90220000 | H300: 45513 | I300: Ampm Padaria Compacta Fachada 2025 | J300: GF RS | K300: Karine Silveira Boardmann | L300: -30.0318 | M300: -51.2065
A301: 613958 | B301: Rede Furnas Com Combs Ltda | C301: Ativo | D301: Sombrio | E301: SC | F301: Rod Br 101 1320 Km 437 Cxpostal 44 | G301: 88960000 | H301: 37404 | I301: Ampm Padaria Compacta 2025 | J301: GF SC | K301: Simone Franceschi Barreto | L301: -29.108 | M301: -49.6328
A302: 621317 | B302: Charpinel Rocha Conveniencias Ltda | C302: Ativo | D302: Alegre | E302: ES | F302: R Monsenhor Pavesi 153 | G302: 29500000 | H302: 45654 | I302: Loja Ampm 2020 | J302: GF Sudeste | K302: Eduardo Furtado Goncalves | L302: -20.758 | M302: -41.5382
A303: 45876 | B303: Posto Do Guerra Com Combs Ltda | C303: Ativo | D303: Carlos Barbosa | E303: RS | F303: R Buarque De Macedo 3931 | G303: 95185000 | H303: 36161 | I303: Loja Ampm Fachada 2025 | J303: GF RS | K303: Deborah Evelyn Oliveira | L303: -29.2969 | M303: -51.5028
A304: 45946 | B304: Abastecedora De Combustiveis Karen Ltda | C304: Ativo | D304: Porto Alegre | E304: RS | F304: Av Otto Niemeyer 2265 | G304: 91910180 | H304: 43718 | I304: Ampm Padaria Compacta | J304: GF RS | K304: Karine Silveira Boardmann | L304: -30.0318 | M304: -51.2065
A305: 9768 | B305: Posto Ventura Quarto Ltda | C305: Ativo | D305: Ibatiba | E305: ES | F305: Rod Br 262 Km 157 + 600 M | G305: 29395000 | H305: 46021 | I305: Loja Ampm 2025 | J305: GF Sudeste | K305: Eduardo Furtado Goncalves | L305: -20.2347 | M305: -41.5087
... A614: 663541 | B614: Vip Conveniencia Eireli | C614: Ativo | D614: Tucurui | E614: PA | F614: R Alcobaca 01 | G614: 68456730 | H614: 42732 | I614: Ampm Padaria Compacta Fachada 2025 | J614: GF N/NE | K614: Rayanne Dos Santos | L614: -3.7657 | M614: -49.6773
A615: 621019 | B615: Auto Posto Almirante Ltda | C615: Ativo | E615: RS | H615: 46203 | I615: Loja Ampm | J615: GF RS | K615: Karine Silveira Boardmann
A616: 643130 | B616: B.M De O. Pereira Com E Dist De Bebidas | C616: Ativo | D616: Salinopolis | E616: PA | F616: Rod Pa 124 Sn Km 01 | G616: 68721000 | H616: 45927 | I616: Loja Ampm 2025 | J616: GF N/NE | K616: Rayanne Dos Santos | L616: -0.630815 | M616: -47.3465
A617: 620499 | B617: Firmino & Sato Ltda | C617: Ativo | D617: Bandeirantes | E617: PR | F617: Av Bandeirantes 1238 | G617: 86360000 | H617: 46080 | I617: Loja Ampm 2025 | J617: GF PR | K617: Marcela Venegas | L617: -23.1078 | M617: -50.3704
A618: 620162 | B618: Nic Conveniencia Ltda | C618: Ativo | D618: Belem | E618: PA | F618: Av Duque De Caxias 602 | G618: 66093400 | H618: 44818 | I618: Ampm Padaria Compacta 2020 | J618: GF N/NE | K618: Rayanne Dos Santos | L618: -1.4554 | M618: -48.4898
A619: 620105 | B619: E P Conveniencia Ltda | C619: Ativo | D619: Belem | E619: PA | F619: R Jeronimo Pimentel 651 | G619: 66055000 | H619: 40540 | I619: Ampm Padaria Compacta 2025 | J619: GF N/NE | K619: Rayanne Dos Santos | L619: -1.4554 | M619: -48.4898
A620: 627660 | B620: Conveniencias Uniao Ltda | C620: Ativo | D620: Breu Branco | E620: PA | F620: Av Sebastiao Camargo Correa 252 | G620: 68488000 | H620: 41151 | I620: Loja Ampm | J620: GF N/NE | K620: Rayanne Dos Santos | L620: -3.77191 | M620: -49.5735
A621: 620164 | B621: Tt Com Varejista De Produtos Alimentic | C621: Ativo | D621: Belem | E621: PA | F621: Av Joao Paulo Ii 262 A | G621: 66630505 | H621: 40025 | I621: Ampm Padaria Full | J621: GF N/NE | K621: Rayanne Dos Santos | L621: -1.4554 | M621: -48.4898
A622: 610975 | B622: Rede Via Expressa Derosso Combustiveis | C622: Ativo | D622: Curitiba | E622: PR | F622: R Francisco Derosso 3559 | G622: 81720235 | H622: 39934 | I622: Loja Ampm | J622: GF PR | K622: Jheniffer Guimaraes Catafesta | L622: -25.4195 | M622: -49.2646
A623: 664163 | B623: Posto Estrela Ltda - Epp | C623: Ativo | D623: Chapadinha | E623: MA | F623: Av Presidente Vargas 1033 | G623: 65500000 | H623: 42977 | I623: Ampm Padaria Compacta | J623: GF N/NE | K623: Rayanne Dos Santos | L623: -3.73875 | M623: -43.3538
A624: 696133 | B624: J O Posto De Combustiveis Vi Ltda | C624: Ativo | D624: Imperatriz | E624: MA | F624: Av Pedro Neiva De Santana Sn | G624: 65914449 | H624: 44575 | I624: Ampm Padaria Compacta 2020 | J624: GF N/NE | K624: Rayanne Dos Santos | L624: -5.51847 | M624: -47.4777
A625: 627901 | B625: Conveniencia 207 Ltda | C625: Ativo | D625: Palmas | E625: TO | F625: Qd 207 Sul Av Ns 7 Sn Lote 01 Pac | G625: 77015310 | H625: 45868 | I625: Loja Ampm 2025 | J625: GF N/NE | K625: Rayanne Dos Santos | L625: -10.24 | M625: -48.3558
A626: 621575 | B626: Comercio De Combustiveis Bonfim Ltda | C626: Ativo | D626: Campinas | E626: SP | F626: Av Alberto Sarmento 21 | G626: 13070010 | H626: 45644 | I626: Loja Ampm | J626: GF SP Capital | K626: Peterson Da Silva Conceicao | L626: -22.9053 | M626: -47.0659
A627: 620206 | B627: Lagoa, Transp Comercio E Servicos Ltda | C627: Ativo | D627: Macapa | E627: AP | F627: R Odilardo Silva 1894 | G627: 68902650 | H627: 45990 | I627: Loja Ampm 2025 | J627: GF N/NE | K627: Rayanne Dos Santos | L627: 0.034934 | M627: -51.0694
... A679: 638056 | B679: P Rodrigues Alves Sta Rita Do Pardo Ltd | C679: Ativo | D679: Santa Rita Do Pardo | E679: MS | F679: Rod Ms 040 Sn Km 0,5 | G679: 79690000 | H679: 44319 | I679: Loja Ampm | J679: GF SP Interior | K679: Andre Luiz De Medeiros | L679: -21.3016 | M679: -52.8333
A680: 5025 | B680: Brasilia Comercio De Combustiveis Ltda | C680: Ativo | D680: Maringa | E680: PR | F680: Rod Pr-317 5989 | H680: 39982 | I680: Loja Ampm | J680: GF PR | K680: Diego Henrique De Souza | L680: -23.4205 | M680: -51.9333
A681: 621636 | B681: Auto Posto Joia Da Goias Ltda | C681: Ativo | D681: Sao Caetano Do Sul | E681: SP | F681: Av Goias 547 | G681: 9521310 | H681: 39997 | I681: Loja Ampm | J681: GF SP Capital | K681: Camila Vieira Brito De Souza | L681: -23.6229 | M681: -46.5548
A682: 620521 | B682: Msa Petroleo Ltda | C682: Ativo | D682: Dourados | E682: MS | F682: Av Marcelino Pires 4958 | G682: 79840630 | H682: 45838 | I682: Loja Ampm 2025 | J682: GF SP Interior | K682: Andre Luiz De Medeiros | L682: -22.2231 | M682: -54.812
A683: 621518 | B683: Jofer Auto Posto Ltda | C683: Ativo | D683: Franca | E683: SP | F683: Av Dr Ismael Alonso Alonso 2231 | G683: 14400902 | H683: 39988 | I683: Ampm Padaria Compacta | J683: GF SP Interior | K683: Iara Bianchi Rodrigues Alves | L683: -20.5352 | M683: -47.4039
A684: 621676 | B684: Gdo Participacoes Sa | C684: Ativo | D684: Sao Paulo | E684: SP | F684: R Jose Ramon Urtiza 1230 | G684: 5717270 | H684: 40025 | I684: Loja Ampm Fachada 2020 | J684: GF SP Capital | K684: Flavio Pereira De Almeida | L684: -23.5329 | M684: -46.6395
A685: 686043 | B685: Posto Estrela Da Chapada Ltda | C685: Ativo | D685: Cuiaba | E685: MT | F685: Rod Emanuel Pinheiro Sn Lote 1 A 4 | G685: 78055799 | H685: 45168 | I685: Ampm Padaria Compacta | J685: GF SP Interior | K685: Andre Luiz De Medeiros | L685: -15.601 | M685: -56.0974
A686: 621660 | B686: Gdo Participacoes Sa | C686: Ativo | D686: Sao Paulo | E686: SP | F686: R Jose Ramon Urtiza 995 | G686: 5717270 | H686: 40025 | I686: Ampm Padaria Compacta Fachada 2020 | J686: GF SP Capital | K686: Flavio Pereira De Almeida | L686: -23.5329 | M686: -46.6395
A687: 662486 | B687: Autoposto De Combustiveis Masp Barao Lt | C687: Ativo | D687: Rondonopolis | E687: MT | F687: R Rio Branco 1737 | G687: 78710100 | H687: 45012 | I687: Ampm Padaria Compacta | J687: GF SP Interior | K687: Andre Luiz De Medeiros | L687: -16.4673 | M687: -54.6372
A688: 621678 | B688: Capela Conveniencia Ltda | C688: Ativo | D688: Ribeirao Preto | E688: SP | F688: R Quintino Bocaiuva 601 | G688: 14015160 | H688: 45412 | I688: Ampm Padaria Compacta 2020 | J688: GF SP Interior | K688: Iara Bianchi Rodrigues Alves | L688: -21.1699 | M688: -47.8099
A689: 662487 | B689: Ap De Combustiveis Masp Correa Ltda | C689: Ativo | D689: Rondonopolis | E689: MT | F689: Av Presidente Kennedy 1830 | G689: 78700300 | H689: 45012 | I689: Ampm Padaria Compacta | J689: GF SP Interior | K689: Andre Luiz De Medeiros | L689: -16.4673 | M689: -54.6372
A690: 621664 | B690: J J P Conveniencia Ltda | C690: Ativo | D690: Paulinia | E690: SP | F690: Av Presidente Getulio Vargas 910 | G690: 13140482 | H690: 39983 | I690: Ampm Padaria Compacta | J690: GF SP Interior | K690: Gabriela Wendt Farias | L690: -22.7542 | M690: -47.1488
A691: 6688 | B691: Ap De Combustiveis Masp Dom Pedro Ltda | C691: Ativo | D691: Rondonopolis | E691: MT | F691: R Dom Pedro Ii 1139 Qd 34 Lt1 | G691: 78700220 | H691: 45012 | I691: Ampm Padaria Compacta | J691: GF SP Interior | K691: Andre Luiz De Medeiros | L691: -16.4673 | M691: -54.6372
A692: 620932 | B692: Posto De Servicos Onzi Ltda | C692: Ativo | D692: Caxias Do Sul | E692: RS | F692: R Moreira Cesar 1920 | G692: 95034000 | H692: 39978 | I692: Loja Ampm | J692: GF RS | K692: Deborah Evelyn Oliveira | L692: -29.1629 | M692: -51.1792
... A873: 632870 | B873: Auto Posto Nossa Senhora Aparecida Ltda | C873: Ativo | D873: Cacador | E873: SC | F873: R Carlos Speranca 267 | G873: 89500000 | H873: 40801 | I873: Loja Ampm | J873: GF SC | K873: Karine Inaja Winck Da Rocha | L873: -26.7757 | M873: -51.012
A874: 2927 | B874: Auto Posto Band 1 Ltda. | C874: Ativo | D874: Sao Paulo | E874: SP | F874: Av Dos Bandeirantes 3245 | H874: 38078 | I874: Ampm Padaria Full 2025 | J874: GF SP Capital | K874: Flavio Pereira De Almeida | L874: -23.5329 | M874: -46.6395
A875: 620983 | B875: Sim Rede De Postos Ltda | C875: Ativo | D875: Porto Alegre | E875: RS | F875: Av Dos Estados 2341 | G875: 90200001 | H875: 41074 | I875: Loja Ampm 2025 | J875: GF RS | K875: Mariana Da Costa Dale | L875: -30.0318 | M875: -51.2065
A876: 103903 | B876: Gdo Participacoes Sa | C876: Ativo | D876: Sao Paulo | E876: SP | F876: R Canario, 674 | G876: 4521003 | H876: 45286 | I876: Loja Ampm 2020 | J876: GF SP Capital | K876: Flavio Pereira De Almeida | L876: -23.5329 | M876: -46.6395
A877: 631789 | B877: Auto Posto V Y Ltda | C877: Ativo | D877: Londrina | E877: PR | F877: Av Ayrton Senna Da Silva 650 | G877: 86050460 | H877: 41257 | I877: Ampm Padaria Full | J877: GF PR | K877: Marcela Venegas | L877: -23.304 | M877: -51.1691
A878: 644009 | B878: Gdo Participacoes Sa | C878: Ativo | D878: Sao Paulo | E878: SP | F878: R Catumbi 379 | G878: 3021000 | H878: 45286 | I878: Loja Ampm 2025 | J878: GF SP Capital | K878: Flavio Pereira De Almeida | L878: -23.5329 | M878: -46.6395
A879: 697022 | B879: Auto Posto Formula 3 Ltda | C879: Ativo | D879: Santos | E879: SP | F879: R Silva Jardim 380 | G879: 11015020 | H879: 44770 | I879: Ampm Padaria Compacta 2025 | J879: GF SP Capital | K879: Flavio Pereira De Almeida | L879: -23.9535 | M879: -46.335
A880: 613601 | B880: V12 Com De Combs & Conveniencia Ltda. | C880: Ativo | D880: Caxias Do Sul | E880: RS | F880: R Rodrigues Alves 2465 | G880: 95076670 | H880: 40758 | I880: Loja Ampm 2025 | J880: GF RS | K880: Deborah Evelyn Oliveira | L880: -29.1629 | M880: -51.1792
A881: 707727 | B881: Auto Posto Edroma Ltda. | C881: Ativo | D881: Sao Paulo | E881: SP | F881: Estr De Itapecerica 5900 | G881: 5858000 | H881: 45287 | I881: Ampm Padaria Compacta 2025 | J881: GF SP Capital | K881: Flavio Pereira De Almeida | L881: -23.5329 | M881: -46.6395
A882: 621700 | B882: Columbus Comercio De Combustiveis Ltda | C882: Ativo | D882: Piracicaba | E882: SP | F882: R Saldanha Marinho 645 | G882: 13416320 | H882: 44702 | I882: Ampm Padaria Compacta | J882: GF SP Capital | K882: Lucas Ramos Dos Santos | L882: -22.7338 | M882: -47.6476
A883: 663403 | B883: Centro Automotivo Gabriel Saraiva Ltda | C883: Ativo | D883: Sao Paulo | E883: SP | F883: Av Sadamu Inoue 6170 | G883: 4865005 | H883: 43098 | I883: Ampm Padaria Compacta 2025 | J883: GF SP Capital | K883: Flavio Pereira De Almeida | L883: -23.5329 | M883: -46.6395
A884: 631729 | B884: Auto Posto Horizonte Azul Ltda | C884: Ativo | D884: Osasco | E884: SP | F884: R Padre Vicente Melillo 1386 | G884: 6030003 | H884: 41517 | I884: Loja Ampm | J884: GF SP Capital | K884: Peterson Da Silva Conceicao | L884: -23.5324 | M884: -46.7916
A885: 620484 | B885: Auto Posto Bsv Vi Ltda | C885: Ativo | D885: Curitiba | E885: PR | F885: R Delegado Leopoldo Belczak 843 | G885: 82800220 | H885: 45542 | I885: Loja Ampm 2025 | J885: GF PR | K885: Jheniffer Guimaraes Catafesta | L885: -25.4195 | M885: -49.2646
A886: 694279 | B886: Centro Automotivo Pilar Do Tiete Ltda | C886: Ativo | D886: Sao Paulo | E886: SP | F886: R Dr Edgard Theotonio Santana 492 | G886: 1140030 | H886: 44702 | I886: Ampm Padaria Full 2025 | J886: GF SP Capital | K886: Flavio Pereira De Almeida | L886: -23.5329 | M886: -46.6395
... A1143: 621006 | B1143: Sbr Comercio De Combustiveis Ltda | C1143: Ativo | D1143: Lages | E1143: SC | F1143: Av Marechal Floriano 1511 | G1143: 88503190 | H1143: 42205 | I1143: Ampm Padaria Compacta | J1143: GF SC | K1143: Karine Inaja Winck Da Rocha | L1143: -27.815 | M1143: -50.3259
A1144: 613565 | B1144: Comercial Le Mans Transportes E Servico | C1144: Ativo | D1144: Canoas | E1144: RS | F1144: Av Getulio Vargas 2989 | G1144: 92110330 | I1144: Loja Ampm | J1144: GF RS | K1144: Daniela Da Silva Alves | L1144: -29.9128 | M1144: -51.1857
A1145: 705379 | B1145: Auto Posto Corumba Ltda | C1145: Ativo | D1145: Sao Paulo | E1145: SP | F1145: R Corumba 70 | G1145: 1015100 | H1145: 44886 | I1145: Loja Ampm 2020 | J1145: GF SP Capital | K1145: Nil Dos Santos Guimaraes | L1145: -23.5329 | M1145: -46.6395
A1146: 620763 | B1146: Dom Pedro Ii Com De Combs E Lubrif Ltda | C1146: Ativo | D1146: Ponta Grossa | E1146: PR | F1146: R Dom Pedro Ii 700 | G1146: 84053000 | H1146: 42188 | I1146: Ampm Padaria Compacta | J1146: GF PR | K1146: Nathalie Voigt | L1146: -25.0916 | M1146: -50.1668
A1147: 705734 | B1147: Auto Posto Bandeira De Santa Tereza | C1147: Ativo | D1147: Carapicuiba | E1147: SP | F1147: R Eduardo Augusto Mesquita 1147 | G1147: 6340380 | H1147: 45596 | I1147: Ampm Fresh 2025 | J1147: GF SP Capital | K1147: Nil Dos Santos Guimaraes | L1147: -23.5235 | M1147: -46.8407
A1148: 21785 | B1148: Auto Posto Lapeano Ii Ltda | C1148: Ativo | D1148: Lapa | E1148: PR | F1148: R Guanabara 55 Km 62 | G1148: 83750000 | H1148: 44406 | I1148: Loja Ampm | J1148: GF PR | K1148: Nathalie Voigt | L1148: -25.7671 | M1148: -49.7168
A1149: 16354 | B1149: P Ilhas Do Hawai Ltda | C1149: Ativo | D1149: Sao Paulo | E1149: SP | F1149: Av Imperatriz Leopoldina 1864 | G1149: 5305003 | H1149: 45281 | I1149: Loja Ampm 2020 | J1149: GF SP Capital | K1149: Nil Dos Santos Guimaraes | L1149: -23.5329 | M1149: -46.6395
A1150: 620532 | B1150: Posto Monte Carlo Jk Ltda - Epp | C1150: Ativo | D1150: Sao Jose Do Rio Preto | E1150: SP | F1150: Av P. Jusc. K. De Oliveira 1111 | G1150: 15093100 | H1150: 42185 | I1150: Ampm Padaria Compacta 2020 | J1150: GF SP Interior | K1150: Bianca Garcia Panchame Da Silveira | L1150: -20.8113 | M1150: -49.3758
A1151: 688555 | B1151: Auto Posto Urus Ltda | C1151: Ativo | D1151: Sao Paulo | E1151: SP | F1151: Av Vitor Manzini 450 | G1151: 4745060 | H1151: 44426 | I1151: Loja Ampm | J1151: GF SP Capital | K1151: Nil Dos Santos Guimaraes | L1151: -23.5329 | M1151: -46.6395
A1152: 652800 | B1152: Auto Posto Safra De Osasco Ltda | C1152: Ativo | D1152: Osasco | E1152: SP | F1152: R Agop Guzelian 505 | G1152: 6213130 | H1152: 45281 | I1152: Ampm Padaria Compacta | J1152: GF SP Capital | K1152: Nil Dos Santos Guimaraes | L1152: -23.5324 | M1152: -46.7916
A1153: 36816 | B1153: Nossa Senhora Da Saude Conveniencia | C1153: Ativo | D1153: Sao Paulo | E1153: SP | F1153: Av Bosque Da Saude 639 | G1153: 4142091 | H1153: 42240 | I1153: Loja Ampm | J1153: GF SP Capital | K1153: Vivian Ianhez | L1153: -23.5329 | M1153: -46.6395
A1154: 653161 | B1154: Auto Posto Parada 688 Ltda | C1154: Ativo | D1154: Sao Paulo | E1154: SP | F1154: Av Parada Pinto 688 | G1154: 2611002 | H1154: 44680 | I1154: Loja Ampm 2020 | J1154: GF SP Capital | K1154: Nil Dos Santos Guimaraes | L1154: -23.5329 | M1154: -46.6395
A1155: 613851 | B1155: Conveniencia Rotula Central Ltda | C1155: Ativo | D1155: Frederico Westphalen | E1155: RS | F1155: R Mauricio Cardoso 106 | G1155: 98400000 | H1155: 42522 | I1155: Ampm Padaria Compacta 2025 | J1155: GF RS | K1155: Ivo Daninger Penna | L1155: -27.3586 | M1155: -53.3958
A1156: 106604 | B1156: Matrinxa Conveniencia Ltda | C1156: Ativo | D1156: Carapicuiba | E1156: SP | F1156: Estr Da Fazendinha 2505 | G1156: 6320000 | H1156: 42366 | I1156: Loja Ampm Fachada 2025 | J1156: GF SP Capital | K1156: Peterson Da Silva Conceicao | L1156: -23.5235 | M1156: -46.8407
... A1337: 2398 | B1337: Rocco Comercial De Combustiveis Ltda | C1337: Ativo | D1337: Piracicaba | E1337: SP | F1337: Av Armando Cesare Dedini 710 | G1337: 13405268 | H1337: 45801 | I1337: Ampm Padaria Compacta 2020 | J1337: GF SP Interior | K1337: Diego Marcondes De Mello Rippi | L1337: -22.7338 | M1337: -47.6476
A1338: 14422 | B1338: Auto Posto Bella Vista De Campinas Ltda | C1338: Ativo | D1338: Campinas | E1338: SP | F1338: Av Julio Prestes 326 | H1338: 46172 | I1338: Ampm Box 2025 | J1338: GF SP Interior | K1338: Diego Marcondes De Mello Rippi | L1338: -22.9053 | M1338: -47.0659
A1339: 15774 | B1339: Flex Loja De Conveniencia Eireli - Me | C1339: Ativo | D1339: Cosmopolis | E1339: SP | F1339: R Campinas 1000 | G1339: 13150000 | H1339: 44194 | I1339: Ampm Padaria Compacta 2020 | J1339: GF SP Interior | K1339: Gabriela Wendt Farias | L1339: -22.6419 | M1339: -47.1926
...

Sheet Previsao_Inauguracao
A1: Status | B1: PV ABADI | C1: Razão Social | D1: Gerência de Franquia | E1: Consultor de Franquia | F1: Consultor_Possivel_Instrutor | G1: Previsão Inauguração | H1: UF | I1: Município | J1: Pipeline | K1: Modelo de Loja | L1: Dias de Treinamento | M1: Latitude | N1: Longitude
A2: Negociação | B2: 4008 | C2: Posto Novo Batel Ltda | D2: GF PR | E2: Nathalie Voigt | G2: 01/06/2026 | H2: PR | I2: Curitiba | J2: Pizza Hut | K2: Padaria | L2: 5 | M2: -25.4195 | N2: -49.2646
A3: Implantação | B3: 3136 | C3: Auto Posto Aventador Ltda | D3: GF PR | E3: Jheniffer Guimaraes Catafesta | G3: 01/06/2026 | H3: PR | I3: Curitiba | J3: Pizza Hut | K3: Padaria | L3: 5 | M3: -25.4195 | N3: -49.2646
A4: Negociação | B4: 670164 | C4: Centro Automotivo Blue Machine Ltda | D4: GF SP Capital | E4: Lucas Ramos Dos Santos | G4: 01/06/2026 | H4: SP | I4: Sao Paulo | J4: Pizza Hut | K4: Padaria | L4: 5 | M4: -23.5329 | N4: -46.6395
A5: Negociação | B5: 2633 | C5: Auto Posto Petrosolo Ltda | D5: GF PR | E5: Marcela Venegas | F5: Marcela Lourenço | G5: 01/06/2026 | H5: PR | I5: Londrina | J5: Pizza Hut | K5: Padaria | L5: 5 | M5: -23.304 | N5: -51.1691
A6: Negociação | B6: 615250 | C6: Longhi Rede De Varejo Ltda. | D6: GF RS | E6: Deborah Evelyn Oliveira | G6: 01/06/2026 | H6: RS | I6: Caxias Do Sul | J6: Pizza Hut | K6: Padaria | L6: 5 | M6: -29.1629 | N6: -51.1792
A7: Negociação | B7: 607663 | C7: H Lang Filho Comercio Representacoes E | D7: GF RS | E7: Ruann Goulart Tadiello | G7: 01/06/2026 | H7: RS | I7: Pelotas | J7: Pizza Hut | K7: Café | L7: 3 | M7: -31.7649 | N7: -52.3371
A8: Negociação | B8: 614469 | C8: Fauri Comercio De Combustiveis Ltda | D8: GF RS | E8: Marcelo De Abreu Sager | G8: 01/06/2026 | H8: RS | I8: Porto Alegre | J8: Pizza Hut | K8: Padaria | L8: 5 | M8: -30.0318 | N8: -51.2065
A9: Negociação | B9: 616571 | C9: Garagem Belem Ltda | D9: GF RS | E9: Mariana Da Costa Dale | G9: 01/06/2026 | H9: RS | I9: Porto Alegre | J9: Pizza Hut | K9: Café | L9: 3 | M9: -30.0318 | N9: -51.2065
A10: Negociação | B10: 23405 | C10: Posto Jotaka Comercio De Combs Ltda | D10: GF PR | E10: Diego Henrique De Souza | F10: Diego Henrique de Souza | G10: 01/06/2026 | H10: PR | I10: Maringa | J10: Pizza Hut | K10: Padaria | L10: 5 | M10: -23.4205 | N10: -51.9333
A11: Implantação | B11: 404887 | C11: Champagnat Conveniencia Ltda | D11: GF Sudeste | E11: Eduardo Furtado Goncalves | G11: 01/06/2026 | H11: ES | I11: Vila Velha | J11: Pizza Hut | K11: Padaria | L11: 5 | M11: -20.3417 | N11: -40.2875
A12: Negociação | B12: 631557 | C12: Posto De Combustiveis Dal Ri Ltda. | D12: GF RS | E12: Filipe Almeida Candido Da Silva | G12: 01/06/2026 | H12: RS | I12: Santa Maria | J12: Pizza Hut | K12: Café | L12: 3 | M12: -29.6868 | N12: -53.8149
A13: Negociação | B13: 614155 | C13: Com Maqs Combs Pitangueira Ltda | D13: GF RS | E13: Filipe Almeida Candido Da Silva | G13: 01/06/2026 | H13: RS | I13: Itaqui | J13: Pizza Hut | K13: Padaria | L13: 5 | M13: -29.1311 | N13: -56.5515
A14: Negociação | B14: 601535 | C14: Posto Linha Verde Ltda | D14: GF RS | E14: Karine Silveira Boardmann | G14: 01/06/2026 | H14: RS | I14: Porto Alegre | J14: Pizza Hut | K14: Padaria | L14: 5 | M14: -30.0318 | N14: -51.2065
A15: Implantação | B15: 613958 | C15: Rede Furnas Com Combs Ltda | D15: GF SC | E15: Simone Franceschi Barreto | F15: Simone Franceschi Barreto | G15: 01/06/2026 | H15: SC | I15: Sombrio | J15: Pizza Hut | K15: Padaria | L15: 5 | M15: -29.108 | N15: -49.6328
A16: Negociação | B16: 615552 | C16: Combustiveis Pegasus Ipiranga Ltda | D16: GF RS | E16: Marcelo De Abreu Sager | G16: 01/06/2026 | H16: RS | I16: Porto Alegre | J16: Pizza Hut | K16: Padaria | L16: 5 | M16: -30.0318 | N16: -51.2065
A17: Negociação | B17: 604138 | C17: Abastecedora De Combustiveis Rioxel Ltd | D17: GF RS | E17: Diana Cristina Kahmann | G17: 01/06/2026 | H17: RS | I17: Guaiba | J17: Pizza Hut | K17: Café | L17: 3 | M17: -30.1086 | N17: -51.3233
A18: Implantação | B18: 617994 | C18: Auto Posto Almirante Ltda | D18: GF RS | E18: Karine Silveira Boardmann | G18: 01/06/2026 | H18: RS | I18: Porto Alegre | J18: Pizza Hut | K18: Padaria | L18: 5 | M18: -30.0318 | N18: -51.2065
A19: Implantação | B19: 670597 | C19: Conveniencia Av4 Eireli - Me | D19: GF SP Interior | E19: Leniele Demarque Rossi | G19: 01/06/2026 | H19: SP | I19: Fernandopolis | J19: Pizza Hut | K19: Café | L19: 3 | M19: -20.2806 | N19: -50.2471
A20: Negociação | B20: 614078 | C20: Jp Santa Lucia Comercio De Combustiveis | D20: GF RS | E20: Filipe Almeida Candido Da Silva | G20: 01/06/2026 | H20: RS | I20: Sao Borja | J20: Pizza Hut | K20: Padaria | L20: 5 | M20: -28.6578 | N20: -56.0036
A21: Negociação | B21: 42378 | C21: Sander Comercio De Combustiveis Ltda | D21: GF RS | E21: Deborah Evelyn Oliveira | G21: 01/06/2026 | H21: RS | I21: Caxias Do Sul | J21: Pizza Hut | K21: Café | L21: 3 | M21: -29.1629 | N21: -51.1792
A22: Negociação | B22: 22604 | C22: Fernanda Raquel Lenz Ravanello - Epp | D22: GF PR | E22: Nathalie Voigt | G22: 01/06/2026 | H22: PR | I22: Uniao Da Vitoria | J22: Pizza Hut | K22: Café | L22: 3 | M22: -26.2273 | N22: -51.0873
A23: Negociação | B23: 603597 | C23: Auto Posto Aguia Do Ibirapuera Ltda. | D23: GF SP Capital | E23: Lucas Ramos Dos Santos | G23: 01/06/2026 | H23: SP | I23: Sao Paulo | J23: Pizza Hut | K23: Café | L23: 3 | M23: -23.5329 | N23: -46.6395
A24: Negociação | B24: 616573 | C24: Posto Rede Salvaro 36 Ltda | D24: GF RS | E24: Mariana Da Costa Dale | G24: 01/06/2026 | H24: RS | I24: Novo Hamburgo | J24: Pizza Hut | K24: Café | L24: 3 | M24: -29.6875 | N24: -51.1328
A25: Negociação | B25: 614828 | C25: Posto Linha Verde Ltda | D25: GF RS | E25: Karine Silveira Boardmann | G25: 01/06/2026 | H25: RS | I25: Porto Alegre | J25: Pizza Hut | K25: Padaria | L25: 5 | M25: -30.0318 | N25: -51.2065
A26: Implantação | B26: 625456 | C26: Auto Posto Alfa Ltda | D26: GF PR | E26: Wilds Willians Ozanski Campos | G26: 01/06/2026 | H26: PR | I26: Colombo | J26: Pizza Hut | K26: Café | L26: 3 | M26: -25.2925 | N26: -49.2262
A27: Negociação | B27: 21379 | C27: Auto Posto Salvaro Ii Ltda | D27: GF PR | E27: Mariangela Galvan Silveira | G27: 01/06/2026 | H27: PR | I27: Guarapuava | J27: Pizza Hut | K27: Café | L27: 3 | M27: -25.3902 | N27: -51.4623
... A40: Obra | B40: 36195 | C40: POSTO DE SERVICOS PROFISSIONALISMO LTDA | D40: GF SP Capital | E40: Jessica Passos | G40: 30/06/2026 | H40: SP | I40: Sao Paulo | J40: Implantação | K40: Box Adaptado | L40: 1 | M40: -23.5329 | N40: -46.6395
A41: Obra | B41: 679889 | C41: POSTO IMPERIO DE GUAPI - Antecipado | D41: GF Sudeste | E41: Isabela Leal | G41: 30/06/2026 | H41: RJ | I41: - | J41: Implantação | K41: Box Adaptado | L41: 1
A42: Obra | B42: 610561 | C42: SUPORTE COM DE COMBS E SERVICOS LTDA - Antcipado | D42: GF SP Interior | E42: Leniele Demarque Rossi | G42: 30/06/2026 | H42: SP | I42: Catanduva | J42: Implantação | K42: Box Adaptado | L42: 1 | M42: -21.1314 | N42: -48.977
A43: Obra | B43: 735063 | C43: AUTO POSTO MASTER | D43: GF SP Interior | E43: Thais Viana Silva | G43: 30/06/2026 | H43: SP | I43: Marilia | J43: Implantação | K43: Café | L43: 3 | M43: -22.2171 | N43: -49.9501
A44: Obra | B44: 16332 | C44: POSTO SAO CRISTOVAO DE MARILIA - Antecipado | D44: GF SP Interior | E44: Thais Viana Silva | G44: 30/06/2026 | H44: SP | I44: Marilia | J44: Implantação | K44: Café | L44: 3 | M44: -22.2171 | N44: -49.9501
A45: Obra | B45: 18009 | C45: AUTO POSTO PRIMALE - Antecipado | D45: GF SP Capital | E45: Lyvia Mesquita | G45: 30/06/2026 | H45: SP | I45: Sao Paulo | J45: Implantação | K45: Café | L45: 3 | M45: -23.5329 | N45: -46.6395
A46: Obra | B46: 638235 | C46: AUTO POSTO PÉROLA PRATA LTDA | D46: GF SP Capital | E46: Flavio Almeida | G46: 30/06/2026 | H46: SP | I46: Barueri | J46: Implantação | K46: Box Adaptado | L46: 1 | M46: -23.5057 | N46: -46.879
A47: Negociação | B47: 5251 | C47: A P Capital Ltda | D47: GF PR | E47: Jheniffer Guimaraes Catafesta | G47: 01/07/2026 | H47: PR | I47: Curitiba | J47: Pizza Hut | K47: Padaria | L47: 5 | M47: -25.4195 | N47: -49.2646
A48: Negociação | B48: 3337 | C48: Auto Posto Bca Luiziana Ltda | D48: GF PR | E48: Diego Henrique De Souza | F48: Diego Henrique de Souza | G48: 01/07/2026 | H48: PR | I48: Maringa | J48: Pizza Hut | K48: Padaria | L48: 5 | M48: -23.4205 | N48: -51.9333
A49: Negociação | B49: 3907 | C49: P De Abast E Serv V Marques Ltda | D49: GF Sudeste | E49: Emanuel Francisco Pena | G49: 01/07/2026 | H49: RJ | I49: Rio De Janeiro | J49: Pizza Hut | K49: Padaria | L49: 5 | M49: -22.9129 | N49: -43.2003
A50: Negociação | B50: 18450 | C50: Auto Posto Alvorada Ii Ltda | D50: GF SP Capital | E50: Lyvia Martins Mesquita | G50: 01/07/2026 | H50: SP | I50: Sao Paulo | J50: Pizza Hut | K50: Café | L50: 3 | M50: -23.5329 | N50: -46.6395
A51: Negociação | B51: 621066 | C51: Fabiane Uarte Carvalho Ludtke Ltda | D51: GF RS | E51: Ruann Goulart Tadiello | G51: 01/07/2026 | H51: RS | I51: Turucu | J51: Pizza Hut | K51: Padaria | L51: 5 | M51: -31.4173 | N51: -52.1706
A52: Implantação | B52: 23578 | C52: Rede Furnas Comercio De Combustiveis | D52: GF SC | E52: Simone Franceschi Barreto | F52: Simone Franceschi Barreto | G52: 01/07/2026 | H52: SC | I52: Tubarao | J52: Pizza Hut | K52: Padaria | L52: 5 | M52: -28.4713 | N52: -49.0144
A53: Negociação | B53: 613654 | C53: Ap Safyr Comercial De Combustiveis Ltda | D53: GF RS | E53: Karine Silveira Boardmann | G53: 01/07/2026 | H53: RS | I53: Campo Bom | J53: Pizza Hut | K53: Padaria | L53: 5 | M53: -29.6747 | N53: -51.0606
A54: Negociação | B54: 615026 | C54: L T Nichele Com De Comb Ltda | D54: GF RS | E54: Mariana Da Costa Dale | G54: 01/07/2026 | H54: RS | I54: Porto Alegre | J54: Pizza Hut | K54: Padaria | L54: 5 | M54: -30.0318 | N54: -51.2065
A55: Negociação | B55: 44994 | C55: Comercio De Combustiveis Baseggio Ltda | D55: GF SC | E55: Karine Inaja Winck Da Rocha | G55: 01/07/2026 | H55: SC | I55: Concordia | J55: Pizza Hut | K55: Padaria | L55: 5 | M55: -27.2335 | N55: -52.026
A56: Negociação | B56: 100070 | C56: P Turistico Do Jaragua | D56: GF SP Capital | E56: Priscila Teixeira Da Silva Vilarina | G56: 01/07/2026 | H56: SP | I56: Sao Paulo | J56: Pizza Hut | K56: Café | L56: 3 | M56: -23.5329 | N56: -46.6395
A57: Negociação | B57: 614057 | C57: Sander Comercio De Combustiveis Ltda | D57: GF RS | E57: Daniela Da Silva Alves | G57: 01/07/2026 | H57: RS | I57: Capao Da Canoa | J57: Pizza Hut | K57: Café | L57: 3 | M57: -29.7642 | N57: -50.0282
A58: Negociação | B58: 615504 | C58: Sander Comercio De Combustiveis Ltda | D58: GF RS | E58: Deborah Evelyn Oliveira | G58: 01/07/2026 | H58: RS | I58: Gramado | J58: Pizza Hut | K58: Café | L58: 3 | M58: -29.3734 | N58: -50.8762
A59: Negociação | B59: 609661 | C59: Posto Do Gus Comercio Combustiveis Ltda | D59: GF SC | E59: Paula Morais Da Silva | G59: 01/07/2026 | H59: SC | I59: Florianopolis | J59: Pizza Hut | K59: Padaria | L59: 5 | M59: -27.5945 | N59: -48.5477
A60: Negociação | B60: 614181 | C60: Auto Posto Bittencourt Ltda | D60: GF RS | E60: Filipe Almeida Candido Da Silva | G60: 01/07/2026 | H60: RS | I60: Santa Maria | J60: Pizza Hut | K60: Café | L60: 3 | M60: -29.6868 | N60: -53.8149
A61: Negociação | B61: 12773 | C61: Santa Rita Comercio De Combs Ltda | D61: GF Sudeste | E61: Eduardo Furtado Goncalves | G61: 01/07/2026 | H61: ES | I61: Vitoria | J61: Pizza Hut | K61: Café | L61: 3 | M61: -20.3155 | N61: -40.3128
A62: Negociação | B62: 681535 | C62: Posto De Servicos Rosario Ltda | D62: GF PR | E62: Jheniffer Guimaraes Catafesta | G62: 01/07/2026 | H62: PR | I62: Curitiba | J62: Pizza Hut | K62: Café | L62: 3 | M62: -25.4195 | N62: -49.2646
A63: Implantação | B63: 620488 | C63: N A Zen & Cia Ltda | D63: GF PR | E63: Mariangela Galvan Silveira | G63: 01/07/2026 | H63: PR | I63: Cascavel | J63: Pizza Hut | K63: Café | L63: 3 | M63: -24.9573 | N63: -53.459
A64: Negociação | B64: 621388 | C64: Auto Posto Monalisa Ltda | D64: GF Sudeste | E64: Emanuel Francisco Pena | G64: 01/07/2026 | H64: RJ | I64: Rio De Janeiro | J64: Pizza Hut | K64: Box | L64: 1 | M64: -22.9129 | N64: -43.2003
... A71: Negociação | B71: 718591 | C71: Loja De Conveniencia Brothers Birmann L | D71: GF SP Capital | E71: Priscila Teixeira Da Silva Vilarina | G71: 01/07/2026 | H71: SP | I71: Sao Paulo | J71: Pizza Hut | K71: Café | L71: 3 | M71: -23.5329 | N71: -46.6395
A72: Negociação | B72: 620616 | C72: Angelim Loja De Conveniencia Ltda | D72: GF PR | E72: Marcela Venegas | F72: Marcela Lourenço | G72: 01/07/2026 | H72: PR | I72: Rolandia | J72: Pizza Hut | K72: Padaria | L72: 5 | M72: -23.3101 | N72: -51.3659
A73: Negociação | B73: 14158 | C73: Ap Confianca Conveniencia Ltda | D73: GF SP Capital | E73: Vivian Ianhez | G73: 01/07/2026 | H73: SP | I73: Sao Paulo | J73: Pizza Hut | K73: Padaria | L73: 5 | M73: -23.5329 | N73: -46.6395
A74: Negociação | B74: 614998 | C74: Abastecedora De Combustiveis Castelinho | D74: GF RS | E74: Karine Silveira Boardmann | G74: 01/07/2026 | H74: RS | I74: Canoas | J74: Pizza Hut | K74: Café | L74: 3 | M74: -29.9128 | N74: -51.1857
A75: Negociação | B75: 714980 | C75: Gruta Do Horto Loja De Conveniencia | D75: GF SP Capital | E75: Ronyere Braga Silva | G75: 01/07/2026 | H75: SP | I75: Sao Paulo | J75: Pizza Hut | K75: Café | L75: 3 | M75: -23.5329 | N75: -46.6395
A76: Negociação | B76: 701882 | C76: Auto Posto Aldeia Da Praia Ltda | D76: GF Sudeste | E76: Eduardo Furtado Goncalves | G76: 01/07/2026 | H76: ES | I76: Guarapari | J76: Pizza Hut | K76: Café | L76: 3 | M76: -20.6772 | N76: -40.5093
A77: Negociação | B77: 3252 | C77: V Brambila E Cia Ltda | D77: GF PR | E77: Marcela Venegas | F77: Marcela Lourenço | G77: 01/07/2026 | H77: PR | I77: Apucarana | J77: Pizza Hut | K77: Padaria | L77: 5 | M77: -23.55 | N77: -51.4635
A78: Negociação | B78: 723957 | C78: Auto Posto P2 Ltda | D78: GF SC | E78: Paula Morais Da Silva | G78: 01/07/2026 | H78: SC | I78: Tijucas | J78: Pizza Hut | K78: Padaria | L78: 5 | M78: -27.2354 | N78: -48.6322
A79: Negociação | B79: 613711 | C79: Abastecedora De Combustiveis Dias Ltda. | D79: GF RS | E79: Deborah Evelyn Oliveira | G79: 01/07/2026 | H79: RS | I79: Caxias Do Sul | J79: Pizza Hut | K79: Café | L79: 3 | M79: -29.1629 | N79: -51.1792
A80: Negociação | B80: 613876 | C80: Posto de Servicos 2Z Ltda | D80: GF RS | E80: Vago - Op | G80: 01/07/2026 | H80: RS | I80: Porto Alegre | J80: Pizza Hut | K80: Café | L80: 3 | M80: -30.0318 | N80: -51.2065
A81: Negociação | B81: 19669 | C81: Delomeg Conveniencias Ltda | D81: GF PR | E81: Mariangela Galvan Silveira | G81: 01/07/2026 | H81: PR | I81: Foz Do Iguacu | J81: Pizza Hut | K81: Café | L81: 3 | M81: -25.5427 | N81: -54.5827
A82: Negociação | B82: 664984 | C82: Auto Posto Monteiros De Cachoeiras Ltda | D82: GF Sudeste | E82: Isabela De Oliveira Leal | G82: 01/07/2026 | H82: RJ | I82: Cachoeiras De Macacu | J82: Pizza Hut | K82: Café | L82: 3 | M82: -22.4658 | N82: -42.6523
A83: Negociação | B83: 40954 | C83: - | D83: - | E83: - | G83: 01/07/2026 | H83: - | I83: - | J83: Pizza Hut | K83: Café | L83: 3
A84: Obra | B84: 723910 | C84: AUTO POSTO BANDEIRA DO JANDAIA LTDA | D84: GF SP Capital | E84: Nil Guimaraes | G84: 30/07/2026 | H84: SP | I84: Carapicuiba | J84: Implantação | K84: Café | L84: 3 | M84: -23.5235 | N84: -46.8407
A85: Obra | B85: 723622 | C85: AUTO POSTO MIGLIANO LTDA | D85: GF SP Capital | E85: Lucas Ramos | G85: 30/07/2026 | H85: SP | I85: Sao Paulo | J85: Implantação | K85: Café | L85: 3 | M85: -23.5329 | N85: -46.6395
A86: Contrato | B86: 613876 | C86: POSTO DE COMBS FIGUEIRA LTDA | D86: GF RS | E86: Karine | G86: 30/07/2026 | H86: RS | I86: Porto Alegre | J86: Implantação | K86: Café | L86: 3 | M86: -30.0318 | N86: -51.2065
A87: Obra | B87: 620669 | C87: Farias Conveniencia Ltda | D87: GF SP Interior | E87: Andre Medeiros | F87: André Luiz de Medeiros | G87: 30/07/2026 | H87: MS | I87: Jardim | J87: Implantação | K87: Café | L87: 3 | M87: -21.4799 | N87: -56.1489
A88: Contrato | B88: 661064 | C88: POSTO GALO LTDA | D88: GF SC | E88: Marllon | G88: 30/07/2026 | H88: SC | I88: Paulo Lopes | J88: Implantação | K88: Café | L88: 3 | M88: -27.9607 | N88: -48.6864
A89: Obra | B89: 500068 | C89: AUTO POSTO HIKARI LTDA - EPP | D89: GF N/NE | E89: Rayanne Dos Santos | G89: 30/07/2026 | H89: PA | I89: Tome-Acu | J89: Implantação | K89: Café | L89: 3 | M89: -2.41302 | N89: -48.1415
A90: Obra | B90: 664984 | C90: AUTO POSTO MONTEIROS DE CACHOEIRAS LTDA | D90: GF Sudeste | E90: - | G90: 30/07/2026 | H90: MT | I90: - | J90: Implantação | K90: Café | L90: 3
A91: Obra | B91: 717245 | C91: POSTO VILA LTDA | D91: GF Sudeste | E91: - | G91: 30/07/2026 | H91: ES | I91: VARGEM ALTA | J91: Implantação | K91: Café | L91: 3 | M91: -20.669 | N91: -41.0179
A92: Negociação | B92: 641251 | C92: Auto Posto Poli Laranjeiras Ltda | D92: GF SP Capital | E92: Priscila Teixeira Da Silva Vilarina | G92: 01/08/2026 | H92: SP | I92: Caieiras | J92: Pizza Hut | K92: Café | L92: 3 | M92: -23.3607 | N92: -46.7397
A93: Obra | B93: 654251 | C93: POSTO ALEXA LTDA | D93: GF N/NE | E93: Pedro | G93: 28/08/2026 | H93: AL | I93: Sao Sebastiao | J93: Implantação | K93: Café | L93: 3 | M93: -9.93043 | N93: -36.559
A94: Obra | B94: 621480 | C94: POSTO RIGOTTI PETROMINAS LTDA | D94: GF Sudeste | E94: Junio Cesar | G94: 30/08/2026 | H94: MG | I94: Pouso Alegre | J94: Implantação | K94: Café | L94: 3 | M94: -22.2266 | N94: -45.9389
A95: Obra | B95: 19669 | C95: DELOMEG CONVENIÊNCIA LTDA | D95: GF PR | E95: Mariangela | G95: 30/08/2026 | H95: PR | I95: Foz Do Iguacu | J95: Implantação | K95: Padaria | L95: 5 | M95: -25.5427 | N95: -54.5827
A96: Contrato | B96: 648871 | C96: AUTO POSTO BAGUARI LTDA ( COOPERCITRUS UBERL) | D96: GF Sudeste | E96: Antonielle | G96: 30/08/2026 | H96: MG | I96: Uberlandia | J96: Implantação | K96: Café | L96: 3 | M96: -18.9141 | N96: -48.2749
A97: Obra | B97: 5078 | C97: AUTO POSTO BISOL LTDA - ME | D97: GF SP Interior | E97: André Mantuano | G97: 30/08/2026 | H97: MS | I97: Paraiso Das Aguas | J97: Implantação | K97: Café | L97: 3 | M97: -19.0216 | N97: -53.0116
A98: Contrato | B98: 637488 | C98: CAMBUI COM DE DERIV DE PETROLEO LTDA | D98: GF SP Interior | E98: Valquiria | G98: 30/08/2026 | H98: GO | I98: Aparecida De Goiania | J98: Implantação | K98: Café | L98: 3 | M98: -16.8198 | N98: -49.2469
A99: PNE | B99: 14399 | C99: Pedro Branco Ferraro Eireli | D99: GF SP Interior | E99: Iara Bianchi Rodrigues Alves | G99: 30/08/2026 | H99: SP | I99: Ourinhos | J99: Implantação | K99: Café | L99: 3 | M99: -22.9797 | N99: -49.8697
A100: Obra | B100: 721136 | C100: DR PETROLEO LTDA | D100: GF Sudeste | E100: Alexandre Magno | G100: 30/08/2026 | H100: MG | I100: Pirapora | J100: Implantação | K100: Box Adaptado | L100: 1 | M100: -17.3392 | N100: -44.934
A101: PNE | B101: 999999455 | C101: TAJ CONVENIENCIA LTDA | D101: GF Sudeste | E101: Antonielle | G101: 30/08/2026 | H101: - | I101: - | J101: Implantação | K101: Box Adaptado | L101: 1
A102: Obra | B102: 100050 | C102: NN PETROGAL CIDADE | D102: GF SP Capital | E102: Flavio Almeida | G102: 30/08/2026 | H102: SP | I102: - | J102: Implantação | K102: Box Adaptado | L102: 1
A103: Obra | B103: 701579 | C103: AUTO POSTO RIGOTTI & MORAES LTDA | D103: GF Sudeste | E103: Junio Cesar | G103: 30/08/2026 | H103: MG | I103: Pouso Alegre | J103: Implantação | K103: Box Adaptado | L103: 1 | M103: -22.2266 | N103: -45.9389
A104: PNE | B104: 620373 | C104: POSTO JARDIM BOTANICO LTDA | D104: GF SP Interior | E104: Valquiria | G104: 30/08/2026 | H104: GO | I104: Goiania | J104: Implantação | K104: Padaria | L104: 5 | M104: -16.6864 | N104: -49.2643
A105: Contrato | B105: 646174 | C105: POSTO ALEGRE LTDA | D105: GF Sudeste | E105: Eduardo Furtado | G105: 30/08/2026 | H105: ES | I105: Sooretama | J105: Implantação | K105: Box Adaptado | L105: 1 | M105: -19.1897 | N105: -40.0974
A106: PNE | B106: 19013 | C106: AUTO POSTO PASCHOAL ARDITO | D106: GF SP Interior | E106: - | G106: 30/08/2026 | H106: SP | I106: Americana | J106: Implantação | K106: Café | L106: 3 | M106: -22.7374 | N106: -47.3331
A107: Contrato | B107: 42249 | C107: Ecol-Comercial De Petroleo Ltda | D107: GF SP Interior | E107: Iara Bianchi Rodrigues Alves | G107: 30/08/2026 | H107: - | I107: - | J107: Implantação | K107: Box Adaptado | L107: 1
A108: Contrato | B108: 703352 | C108: Antonelli & Vitorino Comercio De Combus | D108: GF SP Interior | E108: Valquiria | G108: 30/08/2026 | H108: GO | I108: Abadiania | J108: Implantação | K108: Café | L108: 3 | M108: -16.197 | N108: -48.7057
A109: PNE | B109: 16372 | C109: AMPM AUTO POSTO PRIMAVERA | D109: GF SP Interior | E109: Iara Bianchi Rodrigues Alves | G109: 30/08/2026 | H109: - | I109: - | J109: Implantação | K109: Padaria | L109: 5
A110: Obra | B110: 723913 | C110: AUTO POSTO BANDEIRA DO CENTRINHO LTDA | D110: GF SP Capital | E110: Nil Guimaraes | G110: 10/09/2026 | H110: SP | I110: Cotia | J110: Implantação | K110: Café | L110: 3 | M110: -23.6022 | N110: -46.919
A111: Obra | B111: 643184 | C111: AUTO POSTO CASCAVEL LTDA | D111: GF SP Interior | E111: Valquiria | G111: 30/09/2026 | H111: GO | I111: Goiania | J111: Implantação | K111: Box Adaptado | L111: 1 | M111: -16.6864 | N111: -49.2643
A112: Obra | B112: 661198 | C112: RTS COMERCIO DE COMBUSTIVEIS LTDA | D112: GF PR | E112: Marcela | G112: 30/09/2026 | H112: PR | I112: Londrina | J112: Implantação | K112: Café | L112: 3 | M112: -23.304 | N112: -51.1691
A113: PNE | B113: 720368 | C113: POSTOS EMAUS COMERCIO E SERVICOS LTDA | D113: GF N/NE | E113: Manuela | G113: 30/09/2026 | H113: RN | I113: Angicos | J113: Implantação | K113: Café | L113: 3 | M113: -5.65792 | N113: -36.6094
A114: Contrato | B114: 641803 | C114: EMANUEL FORTUNATO MEDEIROS FLORES | D114: GF RS | E114: Filipe Almeida | G114: 30/09/2026 | H114: RS | I114: Sao Martinho Da Serra | J114: Implantação | K114: Café | L114: 3 | M114: -29.5397 | N114: -53.859
A115: Contrato | B115: 683819 | C115: POSTOS CHOPPÃO LTDA | D115: GF RS | E115: Marcelo Sager | G115: 30/09/2026 | H115: RS | I115: Feliz | J115: Implantação | K115: Café | L115: 3 | M115: -29.4527 | N115: -51.3032
A116: Contrato | B116: 46234 | C116: LENHART & LENHART | D116: GF RS | E116: Diana Kahmann | G116: 30/09/2026 | H116: RS | I116: Mato Leitao | J116: Implantação | K116: Box Adaptado | L116: 1 | M116: -29.5285 | N116: -52.1278
A117: Obra | B117: 19208 | C117: CARAMURU SERV AUTOM LTDA | D117: GF SP Interior | G117: 30/09/2026 | H117: SP | I117: Ribeirao Preto | J117: Implantação | K117: Café | L117: 3 | M117: -21.1699 | N117: -47.8099
A118: Obra | B118: 22942 | C118: POSTO IRMAOS DA ESTRADA LTDA. | D118: GF SC | E118: Hallmes | G118: 30/09/2026 | H118: SC | I118: Balneario Camboriu | J118: Implantação | K118: Padaria | L118: 5 | M118: -26.9926 | N118: -48.6352
...

Sheet Recomendacao_Deslocamento
A1: PV_ABADI | B1: Razao_Social | C1: Municipio_Loja | D1: UF_Loja | E1: Previsao_Inauguracao | F1: Dias_Treinamento_Necessarios | G1: Ranking_Proximidade | H1: Instrutor_Sugerido | I1: Cidade_Instrutor | J1: UF_Instrutor | K1: Distancia_km_linha_reta
A2: 4008 | B2: Posto Novo Batel Ltda | C2: Curitiba | D2: PR | E2: 01/06/2026 | F2: 5 | G2: 1 | H2: Bruno Souza | I2: Barueri | J2: SP | K2: 321.8
A3: 4008 | B3: Posto Novo Batel Ltda | C3: Curitiba | D3: PR | E3: 01/06/2026 | F3: 5 | G3: 2 | H3: Betânia Cayret Pregnolato | I3: São Paulo | J3: SP | K3: 338.5
A4: 4008 | B4: Posto Novo Batel Ltda | C4: Curitiba | D4: PR | E4: 01/06/2026 | F4: 5 | G4: 3 | H4: Carla Fernandes Dionizio | I4: São Paulo | J4: SP | K4: 338.5
A5: 3136 | B5: Auto Posto Aventador Ltda | C5: Curitiba | D5: PR | E5: 01/06/2026 | F5: 5 | G5: 1 | H5: Bruno Souza | I5: Barueri | J5: SP | K5: 321.8
A6: 3136 | B6: Auto Posto Aventador Ltda | C6: Curitiba | D6: PR | E6: 01/06/2026 | F6: 5 | G6: 2 | H6: Betânia Cayret Pregnolato | I6: São Paulo | J6: SP | K6: 338.5
A7: 3136 | B7: Auto Posto Aventador Ltda | C7: Curitiba | D7: PR | E7: 01/06/2026 | F7: 5 | G7: 3 | H7: Carla Fernandes Dionizio | I7: São Paulo | J7: SP | K7: 338.5
A8: 670164 | B8: Centro Automotivo Blue Machine Ltda | C8: Sao Paulo | D8: SP | E8: 01/06/2026 | F8: 5 | G8: 1 | H8: Betânia Cayret Pregnolato | I8: São Paulo | J8: SP | K8: 0
A9: 670164 | B9: Centro Automotivo Blue Machine Ltda | C9: Sao Paulo | D9: SP | E9: 01/06/2026 | F9: 5 | G9: 2 | H9: Carla Fernandes Dionizio | I9: São Paulo | J9: SP | K9: 0
A10: 670164 | B10: Centro Automotivo Blue Machine Ltda | C10: Sao Paulo | D10: SP | E10: 01/06/2026 | F10: 5 | G10: 3 | H10: Roberta de Cássia Martareli | I10: São Paulo | J10: SP | K10: 0
A11: 2633 | B11: Auto Posto Petrosolo Ltda | C11: Londrina | D11: PR | E11: 01/06/2026 | F11: 5 | G11: 1 | H11: Bruno Souza | I11: Barueri | J11: SP | K11: 438.3
A12: 2633 | B12: Auto Posto Petrosolo Ltda | C12: Londrina | D12: PR | E12: 01/06/2026 | F12: 5 | G12: 2 | H12: Betânia Cayret Pregnolato | I12: São Paulo | J12: SP | K12: 462.9
A13: 2633 | B13: Auto Posto Petrosolo Ltda | C13: Londrina | D13: PR | E13: 01/06/2026 | F13: 5 | G13: 3 | H13: Carla Fernandes Dionizio | I13: São Paulo | J13: SP | K13: 462.9
... A412: 652619 | B412: Posto Guajara Ltda | C412: Capanema | D412: PA | E412: 30/12/2026 | F412: 1 | G412: 3 | H412: Betânia Cayret Pregnolato | I412: São Paulo | J412: SP | K412: 2483.4

Sheet Agenda_Semanal_Sugerida
A1: Instrutor | B1: Semana_Num | C1: Periodo | D1: Ordem_na_Rota | E1: PV_Abadi | F1: Loja | G1: Municipio | H1: UF | I1: Tipo_Necessidade | J1: Dias_Treinamento | K1: Distancia_desde_ponto_anterior_km
A2: Betânia Cayret Pregnolato | B2: 1 | C2: 03/08/2026 a 07/08/2026 | D2: 1 | E2: 14065 | F2: A P Serra De Braganca Ltda | G2: Sao Paulo | H2: SP | I2: Retreinamento | J2: 2 | K2: 0
A3: Betânia Cayret Pregnolato | B3: 1 | C3: 03/08/2026 a 07/08/2026 | D3: 2 | E3: 658759 | F3: Novo Modena Auto Posto Ltda | G3: Sao Paulo | H3: SP | I3: Retreinamento | J3: 2 | K3: 0
A4: Betânia Cayret Pregnolato | B4: 2 | C4: 10/08/2026 a 14/08/2026 | D4: 1 | E4: 719865 | F4: Grupo Majore Paula Auto Posto Ltda | G4: Sao Paulo | H4: SP | I4: Retreinamento | J4: 2 | K4: 0
A5: Betânia Cayret Pregnolato | B5: 2 | C5: 10/08/2026 a 14/08/2026 | D5: 2 | E5: 1142 | F5: Auto Posto Leao De Pirituba Ltda | G5: Sao Paulo | H5: SP | I5: Retreinamento | J5: 2 | K5: 0
A6: Betânia Cayret Pregnolato | B6: 3 | C6: 17/08/2026 a 21/08/2026 | D6: 1 | E6: 660537 | F6: Fast Giant Da Engenheiro Ltda | G6: Sao Paulo | H6: SP | I6: Retreinamento | J6: 2 | K6: 0
A7: Betânia Cayret Pregnolato | B7: 3 | C7: 17/08/2026 a 21/08/2026 | D7: 2 | E7: 678596 | F7: Centro Automotivo Himalaia Ltda | G7: Sao Paulo | H7: SP | I7: Retreinamento | J7: 2 | K7: 0
A8: Betânia Cayret Pregnolato | B8: 4 | C8: 24/08/2026 a 28/08/2026 | D8: 1 | E8: 705591 | F8: Auto Posto Rede Ban 2 Ltda | G8: Sao Paulo | H8: SP | I8: Retreinamento | J8: 2 | K8: 0
A9: Betânia Cayret Pregnolato | B9: 4 | C9: 24/08/2026 a 28/08/2026 | D9: 2 | E9: 621742 | F9: Sigmar Conveniencias Ltda | G9: Sao Paulo | H9: SP | I9: Retreinamento | J9: 2 | K9: 0
A10: Betânia Cayret Pregnolato | B10: 5 | C10: 31/08/2026 a 04/09/2026 | D10: 1 | E10: 670164 | F10: Centro Automotivo Blue Machine Ltda | G10: Sao Paulo | H10: SP | I10: Treinamento Nova Loja (Pizza Hut) | J10: 5 | K10: 0
A11: Betânia Cayret Pregnolato | B11: 6 | C11: 07/09/2026 a 11/09/2026 | D11: 1 | E11: 718591 | F11: Loja De Conveniencia Brothers Birmann L | G11: Sao Paulo | H11: SP | I11: Treinamento Nova Loja (Pizza Hut) | J11: 3 | K11: 0
A12: Betânia Cayret Pregnolato | B12: 7 | C12: 14/09/2026 a 18/09/2026 | D12: 1 | E12: 723622 | F12: AUTO POSTO MIGLIANO LTDA | G12: Sao Paulo | H12: SP | I12: Treinamento Nova Loja (Implantação) | J12: 3 | K12: 0
A13: Betânia Cayret Pregnolato | B13: 8 | C13: 21/09/2026 a 25/09/2026 | D13: 1 | E13: 18450 | F13: Auto Posto Alvorada Ii Ltda | G13: Sao Paulo | H13: SP | I13: Treinamento Nova Loja (Pizza Hut) | J13: 3 | K13: 0
... A372: Roberta de Cássia Martareli | B372: 37 | C372: 12/04/2027 a 16/04/2027 | D372: 1 | E372: 648819 | F372: Auto Posto Independencia Com.Combs.Serv | G372: Belem | H372: PA | I372: Retreinamento | J372: 2 | K372: 2463

Sheet Fila_CallCenter
A1: PV_Abadi | B1: Loja | C1: Municipio | D1: UF | E1: Tipo_Necessidade | F1: Data_Ultimo_Treinamento | G1: Dias_desde_Ultimo_Treinamento | H1: Instrutor_Sugerido | I1: Semana_Sugerida | J1: Telefone_Contato | K1: Status_Contato | L1: Data_do_Contato | M1: Observacoes
A2: 621193 | B2: Conveniencia Rodrigues E Companhia Ltda | C2: Atalaia | D2: AL | E2: Retreinamento | F2: 45786 | G2: 448 | H2: Isabela Paim Ricardo | I2: 19/04/2027 a 23/04/2027 | K2: A Contatar
A3: 621258 | B3: New Star Com De Combs E Lubrifi Ltda | C3: Maceio | D3: AL | E3: Retreinamento | F3: 45643 | G3: 591 | H3: Isabela Paim Ricardo | I3: 05/04/2027 a 09/04/2027 | K3: A Contatar
A4: 621112 | B4: Auto Posto Bariloche Eireli | C4: Maceio | D4: AL | E4: Retreinamento | F4: 45644 | G4: 590 | H4: Isabela Paim Ricardo | I4: 05/04/2027 a 09/04/2027 | K4: A Contatar
A5: 709048 | B5: Beluma Comercio De Combustiveis Ltda | C5: Maceio | D5: AL | E5: Retreinamento | F5: 45777 | G5: 457 | H5: Isabela Paim Ricardo | I5: 12/04/2027 a 16/04/2027 | K5: A Contatar
A6: 665493 | B6: Pratagy Frances Ltda | C6: Marechal Deodoro | D6: AL | E6: Retreinamento | F6: 45783 | G6: 451 | H6: Carla Fernandes Dionizio | I6: 22/03/2027 a 26/03/2027 | K6: A Contatar
A7: 724183 | B7: POSTO SANTA RITA | C7: Rio Largo | D7: AL | E7: Treinamento Nova Loja (Implantação) | H7: Isabela Paim Ricardo | I7: 12/04/2027 a 16/04/2027 | K7: A Contatar
A8: 702900 | B8: TULEMON COMERCIO | C8: Rio Largo | D8: AL | E8: Treinamento Nova Loja (Implantação) | H8: Isabela Paim Ricardo | I8: 19/04/2027 a 23/04/2027 | K8: A Contatar
A9: 654251 | B9: POSTO ALEXA LTDA | C9: Sao Sebastiao | D9: AL | E9: Treinamento Nova Loja (Implantação) | H9: Isabela Paim Ricardo | I9: 15/03/2027 a 19/03/2027 | K9: A Contatar
A10: 646306 | B10: Auto Posto Sabalanga Ltda - Me | C10: Vicosa | D10: AL | E10: Retreinamento | F10: 45849 | G10: 385 | H10: Carla Fernandes Dionizio | I10: 22/03/2027 a 26/03/2027 | K10: A Contatar
A11: 684108 | B11: Mucuripe Varejo Ltda | C11: Manaus | D11: AM | E11: Retreinamento | F11: 45694 | G11: 540 | H11: Carla Fernandes Dionizio | I11: 05/04/2027 a 09/04/2027 | K11: A Contatar
A12: 731313 | B12: MUCURIPE COMERCIO DE COMBS | C12: Manaus | D12: AM | E12: Treinamento Nova Loja (Implantação) | H12: Betânia Cayret Pregnolato | I12: 12/04/2027 a 16/04/2027 | K12: A Contatar
A13: 30141 | B13: Conveniencia Mts Ltda | C13: Salvador | D13: BA | E13: Retreinamento | F13: 45632 | G13: 602 | H13: Roberta de Cássia Martareli | I13: 05/04/2027 a 09/04/2027 | K13: A Contatar
A14: 620305 | B14: Maisbarato - Comercio De Alimentos Ltda | C14: Brasilia | D14: DF | E14: Retreinamento | F14: 45859 | G14: 375 | H14: Isabela Paim Ricardo | I14: 15/03/2027 a 19/03/2027 | K14: A Contatar
A15: 620436 | B15: Maisbarato - Comercio De Alimentos Ltda | C15: Brasilia | D15: DF | E15: Retreinamento | F15: 45861 | G15: 373 | H15: Bruno Souza | I15: 22/03/2027 a 26/03/2027 | K15: A Contatar
A16: 620371 | B16: Loja De Conveniencia Candanga Ltda | C16: Brasilia | D16: DF | E16: Retreinamento | F16: 45568 | G16: 666 | H16: Betânia Cayret Pregnolato | I16: 25/01/2027 a 29/01/2027 | K16: A Contatar
A17: 701821 | B17: Texas Conveniencia Ltda Me | C17: Cariacica | D17: ES | E17: Treinamento Nova Loja (Pizza Hut) | H17: Isabela Paim Ricardo | I17: 14/12/2026 a 18/12/2026 | K17: A Contatar
A18: 701882 | B18: Auto Posto Aldeia Da Praia Ltda | C18: Guarapari | D18: ES | E18: Treinamento Nova Loja (Pizza Hut) | H18: Isabela Paim Ricardo | I18: 30/11/2026 a 04/12/2026 | K18: A Contatar
A19: 621320 | B19: AUTO POSTO ROTA 66 LTDA | C19: Guarapari | D19: ES | E19: Treinamento Nova Loja (Implantação) | H19: Isabela Paim Ricardo | I19: 07/12/2026 a 11/12/2026 | K19: A Contatar
A20: 621412 | B20: Marataizes Conveniencia Ltda | C20: Marataizes | D20: ES | E20: Retreinamento | F20: 45569 | G20: 665 | H20: Isabela Paim Ricardo | I20: 26/10/2026 a 30/10/2026 | K20: A Contatar
A21: 621293 | B21: Auto Posto Paulo Layber Ltda | C21: Piuma | D21: ES | E21: Retreinamento | F21: 45583 | G21: 651 | H21: Isabela Paim Ricardo | I21: 26/10/2026 a 30/10/2026 | K21: A Contatar
A22: 646174 | B22: POSTO ALEGRE LTDA | C22: Sooretama | D22: ES | E22: Treinamento Nova Loja (Implantação) | H22: Isabela Paim Ricardo | I22: 04/01/2027 a 08/01/2027 | K22: A Contatar
A23: 717245 | B23: POSTO VILA LTDA | C23: VARGEM ALTA | D23: ES | E23: Treinamento Nova Loja (Implantação) | H23: Isabela Paim Ricardo | I23: 09/11/2026 a 13/11/2026 | K23: A Contatar
A24: 404887 | B24: Champagnat Conveniencia Ltda | C24: Vila Velha | D24: ES | E24: Treinamento Nova Loja (Pizza Hut) | H24: Isabela Paim Ricardo | I24: 21/12/2026 a 25/12/2026 | K24: A Contatar
A25: 621479 | B25: Convento Conveniencia Ltda | C25: Vitoria | D25: ES | E25: Treinamento Nova Loja (Pizza Hut) | H25: Isabela Paim Ricardo | I25: 28/12/2026 a 01/01/2027 | K25: A Contatar
A26: 12773 | B26: Santa Rita Comercio De Combs Ltda | C26: Vitoria | D26: ES | E26: Treinamento Nova Loja (Pizza Hut) | H26: Isabela Paim Ricardo | I26: 04/01/2027 a 08/01/2027 | K26: A Contatar
A27: 703352 | B27: Antonelli & Vitorino Comercio De Combus | C27: Abadiania | D27: GO | E27: Treinamento Nova Loja (Implantação) | H27: Betânia Cayret Pregnolato | I27: 15/03/2027 a 19/03/2027 | K27: A Contatar
A28: 637488 | B28: CAMBUI COM DE DERIV DE PETROLEO LTDA | C28: Aparecida De Goiania | D28: GO | E28: Treinamento Nova Loja (Implantação) | H28: Betânia Cayret Pregnolato | I28: 08/03/2027 a 12/03/2027 | K28: A Contatar
A29: 687318 | B29: Conveniencia Global Arena Ltda | C29: Goiania | D29: GO | E29: Retreinamento | F29: 45812 | G29: 422 | H29: Carla Fernandes Dionizio | I29: 22/02/2027 a 26/02/2027 | K29: A Contatar
A30: 643183 | B30: Passeio Das Aguas Conveniencia Ltda | C30: Goiania | D30: GO | E30: Retreinamento | F30: 45825 | G30: 409 | H30: Roberta de Cássia Martareli | I30: 15/03/2027 a 19/03/2027 | K30: A Contatar
A31: 620409 | B31: Ferreira Matias Combustiveis I Ltda | C31: Goiania | D31: GO | E31: Retreinamento | F31: 45587 | G31: 647 | H31: Carla Fernandes Dionizio | I31: 28/12/2026 a 01/01/2027 | K31: A Contatar
A32: 620373 | B32: POSTO JARDIM BOTANICO LTDA | C32: Goiania | D32: GO | E32: Treinamento Nova Loja (Implantação) | H32: Bruno Souza | I32: 15/02/2027 a 19/02/2027 | K32: A Contatar
A33: 643184 | B33: AUTO POSTO CASCAVEL LTDA | C33: Goiania | D33: GO | E33: Treinamento Nova Loja (Implantação) | H33: Isabela Paim Ricardo | I33: 18/01/2027 a 22/01/2027 | K33: A Contatar
A34: 636489 | B34: L S Comercio E Servicos Ltda | C34: Sao Luis | D34: MA | E34: Retreinamento | F34: 45804 | G34: 430 | H34: Carla Fernandes Dionizio | I34: 29/03/2027 a 02/04/2027 | K34: A Contatar
A35: 623932 | B35: AGUIAR PETROLEO E LOCACOES LTDA | C35: Sao Luis | D35: MA | E35: Treinamento Nova Loja (Implantação) | H35: Carla Fernandes Dionizio | I35: 29/03/2027 a 02/04/2027 | K35: A Contatar
A36: 7737 | B36: Raja Nobre Loja De Conveniencia Ltda | C36: Belo Horizonte | D36: MG | E36: Retreinamento | F36: 45590 | G36: 644 | H36: Betânia Cayret Pregnolato | I36: 30/11/2026 a 04/12/2026 | K36: A Contatar
A37: 613443 | B37: Conveniencia Nossa Senhora D Bom Despac | C37: Belo Horizonte | D37: MG | E37: Retreinamento | F37: 45807 | G37: 427 | H37: Betânia Cayret Pregnolato | I37: 28/12/2026 a 01/01/2027 | K37: A Contatar
A38: 651045 | B38: Conv.Nossa Senhora Do Bom Despacho Ltda | C38: Betim | D38: MG | E38: Retreinamento | F38: 45806 | G38: 428 | H38: Roberta de Cássia Martareli | I38: 01/02/2027 a 05/02/2027 | K38: A Contatar
A39: 32148 | B39: Capital Conveniencias E Servicos Ltda | C39: Contagem | D39: MG | E39: Retreinamento | F39: 45748 | G39: 486 | H39: Betânia Cayret Pregnolato | I39: 28/12/2026 a 01/01/2027 | K39: A Contatar
A40: 32295 | B40: POSTO ALTO PARANAIBA EIRELI | C40: Monte Carmelo | D40: MG | E40: Treinamento Nova Loja (Implantação) | H40: Carla Fernandes Dionizio | I40: 28/12/2026 a 01/01/2027 | K40: A Contatar
A41: 400166 | B41: Izauro Tadeu De Brito Guimaraes - Me | C41: Montes Claros | D41: MG | E41: Retreinamento | F41: 45581 | G41: 653 | H41: Carla Fernandes Dionizio | I41: 22/02/2027 a 26/02/2027 | K41: A Contatar
A42: 620410 | B42: Costa & Chemello Conveniencias Ltda | C42: Montes Claros | D42: MG | E42: Retreinamento | F42: 45793 | G42: 441 | H42: Roberta de Cássia Martareli | I42: 15/03/2027 a 19/03/2027 | K42: A Contatar
A43: 620272 | B43: Marcelo Siqueira Lemos | C43: Nova Lima | D43: MG | E43: Retreinamento | F43: 45607 | G43: 627 | H43: Roberta de Cássia Martareli | I43: 01/02/2027 a 05/02/2027 | K43: A Contatar
A44: 635528 | B44: Nilton Rastelli | C44: Ouro Fino | D44: MG | E44: Retreinamento | F44: 45625 | G44: 609 | H44: Carla Fernandes Dionizio | I44: 28/09/2026 a 02/10/2026 | K44: A Contatar
A45: 721136 | B45: DR PETROLEO LTDA | C45: Pirapora | D45: MG | E45: Treinamento Nova Loja (Implantação) | H45: Isabela Paim Ricardo | I45: 16/11/2026 a 20/11/2026 | K45: A Contatar
A46: 621480 | B46: POSTO RIGOTTI PETROMINAS LTDA | C46: Pouso Alegre | D46: MG | E46: Treinamento Nova Loja (Implantação) | H46: Betânia Cayret Pregnolato | I46: 26/10/2026 a 30/10/2026 | K46: A Contatar
A47: 701579 | B47: AUTO POSTO RIGOTTI & MORAES LTDA | C47: Pouso Alegre | D47: MG | E47: Treinamento Nova Loja (Implantação) | H47: Bruno Souza | I47: 14/09/2026 a 18/09/2026 | K47: A Contatar
A48: 617785 | B48: AUTO POSTO SABARA LTDA | C48: Sabara | D48: MG | E48: Treinamento Nova Loja (Implantação) | H48: Isabela Paim Ricardo | I48: 16/11/2026 a 20/11/2026 | K48: A Contatar
A49: 8183 | B49: JACARE A P LTDA | C49: Sao Sebastiao Do Paraiso | D49: MG | E49: Treinamento Nova Loja (Implantação) | H49: Roberta de Cássia Martareli | I49: 02/11/2026 a 06/11/2026 | K49: A Contatar
A50: 8340 | B50: Expresso Conveniencia Lanchonete & Merc | C50: Uberaba | D50: MG | E50: Retreinamento | F50: 45699 | G50: 535 | H50: Roberta de Cássia Martareli | I50: 18/01/2027 a 22/01/2027 | K50: A Contatar
A51: 8332 | B51: Gava Conveniencias Ltda | C51: Uberaba | D51: MG | E51: Retreinamento | F51: 45595 | G51: 639 | H51: Carla Fernandes Dionizio | I51: 16/11/2026 a 20/11/2026 | K51: A Contatar
A52: 620249 | B52: Expresso Conveniencia Lanchonete & Merc | C52: Uberaba | D52: MG | E52: Retreinamento | F52: 45702 | G52: 532 | H52: Carla Fernandes Dionizio | I52: 05/10/2026 a 09/10/2026 | K52: A Contatar
A53: 616022 | B53: Expresso Conveniencia Lanchonete & Merc | C53: Uberlandia | D53: MG | E53: Retreinamento | F53: 45710 | G53: 524 | H53: Bruno Souza | I53: 18/01/2027 a 22/01/2027 | K53: A Contatar
A54: 632730 | B54: Expres Conveni Lanch & Merc Joao Naves | C54: Uberlandia | D54: MG | E54: Retreinamento | F54: 45707 | G54: 527 | H54: Roberta de Cássia Martareli | I54: 18/01/2027 a 22/01/2027 | K54: A Contatar
A55: 632577 | B55: Jardim Veneza Conveniencia | C55: Uberlandia | D55: MG | E55: Treinamento Nova Loja (Pizza Hut) | H55: Bruno Souza | I55: 18/01/2027 a 22/01/2027 | K55: A Contatar
A56: 648871 | B56: AUTO POSTO BAGUARI LTDA ( COOPERCITRUS UBERL) | C56: Uberlandia | D56: MG | E56: Treinamento Nova Loja (Implantação) | H56: Roberta de Cássia Martareli | I56: 15/02/2027 a 19/02/2027 | K56: A Contatar
A57: 620348 | B57: Stop & Shop Mg 10 Conveniencia Ltda | C57: Vespasiano | D57: MG | E57: Retreinamento | F57: 45715 | G57: 519 | H57: Betânia Cayret Pregnolato | I57: 25/01/2027 a 29/01/2027 | K57: A Contatar
A58: 645491 | B58: Conveniencia Ecologico Ltda | C58: Campo Grande | D58: MS | E58: Retreinamento | F58: 45549 | G58: 685 | H58: Bruno Souza | I58: 01/03/2027 a 05/03/2027 | K58: A Contatar
A59: 695696 | B59: Conveniencia Afonso Pena Ltda | C59: Campo Grande | D59: MS | E59: Retreinamento | F59: 45814 | G59: 420 | H59: Carla Fernandes Dionizio | I59: 15/03/2027 a 19/03/2027 | K59: A Contatar
A60: 634497 | B60: Baffs Conveniencia Mato Grosso Ltda | C60: Campo Grande | D60: MS | E60: Retreinamento | F60: 45814 | G60: 420 | H60: Bruno Souza | I60: 22/03/2027 a 26/03/2027 | K60: A Contatar
A61: 635867 | B61: Baffs Conveniencia Rita Vieira Ltda | C61: Campo Grande | D61: MS | E61: Retreinamento | F61: 45625 | G61: 609 | H61: Betânia Cayret Pregnolato | I61: 01/02/2027 a 05/02/2027 | K61: A Contatar
A62: 620669 | B62: Farias Conveniencia Ltda | C62: Jardim | D62: MS | E62: Treinamento Nova Loja (Implantação) | H62: Carla Fernandes Dionizio | I62: 15/03/2027 a 19/03/2027 | K62: A Contatar
A63: 5078 | B63: AUTO POSTO BISOL LTDA - ME | C63: Paraiso Das Aguas | D63: MS | E63: Treinamento Nova Loja (Implantação) | H63: Bruno Souza | I63: 01/03/2027 a 05/03/2027 | K63: A Contatar
A64: 648819 | B64: Auto Posto Independencia Com.Combs.Serv | C64: Belem | D64: PA | E64: Retreinamento | F64: 45789 | G64: 445 | H64: Roberta de Cássia Martareli | I64: 12/04/2027 a 16/04/2027 | K64: A Contatar
A65: 620125 | B65: Auto Posto Conselheiro Comercio | C65: Belem | D65: PA | E65: Retreinamento | F65: 45789 | G65: 445 | H65: Bruno Souza | I65: 05/04/2027 a 09/04/2027 | K65: A Contatar
A66: 620106 | B66: Posto Girassol Ltda | C66: Belem | D66: PA | E66: Retreinamento | F66: 45789 | G66: 445 | H66: Betânia Cayret Pregnolato | I66: 05/04/2027 a 09/04/2027 | K66: A Contatar
A67: 620143 | B67: Auto Posto Cedro Ltda | C67: Belem | D67: PA | E67: Retreinamento | F67: 45805 | G67: 429 | H67: Carla Fernandes Dionizio | I67: 05/04/2027 a 09/04/2027 | K67: A Contatar
A68: 652619 | B68: Posto Guajara Ltda | C68: Capanema | D68: PA | E68: Treinamento Nova Loja (Implantação) | H68: Betânia Cayret Pregnolato | I68: 05/04/2027 a 09/04/2027 | K68: A Contatar
A69: 500068 | B69: AUTO POSTO HIKARI LTDA - EPP | C69: Tome-Acu | D69: PA | E69: Treinamento Nova Loja (Implantação) | H69: Isabela Paim Ricardo | I69: 10/05/2027 a 14/05/2027 | K69: A Contatar
A70: 3252 | B70: V Brambila E Cia Ltda | C70: Apucarana | D70: PR | E70: Treinamento Nova Loja (Pizza Hut) | H70: Betânia Cayret Pregnolato | I70: 04/01/2027 a 08/01/2027 | K70: A Contatar
A71: 22725 | B71: Auto Posto Principal Ltda | C71: Araucaria | D71: PR | E71: Retreinamento | F71: 45569 | G71: 665 | H71: Carla Fernandes Dionizio | I71: 26/10/2026 a 30/10/2026 | K71: A Contatar
A72: 620489 | B72: Roso & Filhos Ltda | C72: Capanema | D72: PR | E72: Retreinamento | F72: 45568 | G72: 666 | H72: Betânia Cayret Pregnolato | I72: 15/02/2027 a 19/02/2027 | K72: A Contatar
A73: 620712 | B73: Botanico Comercio De Combustivel Ltda | C73: Cascavel | D73: PR | E73: Retreinamento | F73: 45567 | G73: 667 | H73: Bruno Souza | I73: 25/01/2027 a 29/01/2027 | K73: A Contatar
A74: 620488 | B74: N A Zen & Cia Ltda | C74: Cascavel | D74: PR | E74: Treinamento Nova Loja (Pizza Hut) | H74: Bruno Souza | I74: 25/01/2027 a 29/01/2027 | K74: A Contatar
A75: 625456 | B75: Auto Posto Alfa Ltda | C75: Colombo | D75: PR | E75: Treinamento Nova Loja (Pizza Hut) | H75: Betânia Cayret Pregnolato | I75: 09/11/2026 a 13/11/2026 | K75: A Contatar
A76: 47123 | B76: Auto Posto Vpc Ltda | C76: Curitiba | D76: PR | E76: Retreinamento | F76: 45834 | G76: 400 | H76: Betânia Cayret Pregnolato | I76: 09/11/2026 a 13/11/2026 | K76: A Contatar
A77: 22629 | B77: Auto Posto Afonso Pena Ltda | C77: Curitiba | D77: PR | E77: Retreinamento | F77: 45825 | G77: 409 | H77: Bruno Souza | I77: 05/10/2026 a 09/10/2026 | K77: A Contatar
A78: 3271 | B78: Auto Posto Tio Zico Viii Ltda | C78: Curitiba | D78: PR | E78: Retreinamento | F78: 45685 | G78: 549 | H78: Leonardo da Silva Azevedo | I78: 19/04/2027 a 23/04/2027 | K78: A Contatar
A79: 620562 | B79: Posto Silva Jardim Ltda | C79: Curitiba | D79: PR | E79: Retreinamento | F79: 45688 | G79: 546 | H79: Bruno Souza | I79: 05/10/2026 a 09/10/2026 | K79: A Contatar
A80: 620484 | B80: Auto Posto Bsv Vi Ltda | C80: Curitiba | D80: PR | E80: Retreinamento | F80: 45553 | G80: 681 | H80: Betânia Cayret Pregnolato | I80: 16/11/2026 a 20/11/2026 | K80: A Contatar
A81: 662844 | B81: Pvh Petro Ltda | C81: Curitiba | D81: PR | E81: Retreinamento | F81: 45699 | G81: 535 | H81: Betânia Cayret Pregnolato | I81: 16/11/2026 a 20/11/2026 | K81: A Contatar
A82: 4008 | B82: Posto Novo Batel Ltda | C82: Curitiba | D82: PR | E82: Treinamento Nova Loja (Pizza Hut) | H82: Roberta de Cássia Martareli | I82: 07/12/2026 a 11/12/2026 | K82: A Contatar
A83: 3136 | B83: Auto Posto Aventador Ltda | C83: Curitiba | D83: PR | E83: Treinamento Nova Loja (Pizza Hut) | H83: Bruno Souza | I83: 12/10/2026 a 16/10/2026 | K83: A Contatar
A84: 620635 | B84: Tic Posto Ltda | C84: Curitiba | D84: PR | E84: Treinamento Nova Loja (Pizza Hut) | H84: Carla Fernandes Dionizio | I84: 12/10/2026 a 16/10/2026 | K84: A Contatar
A85: 200629 | B85: Auto Posto Due Fratelli Ltda | C85: Curitiba | D85: PR | E85: Treinamento Nova Loja (Pizza Hut) | H85: Roberta de Cássia Martareli | I85: 16/11/2026 a 20/11/2026 | K85: A Contatar
A86: 701799 | B86: Ducati Auto Posto Ltda | C86: Curitiba | D86: PR | E86: Treinamento Nova Loja (Pizza Hut) | H86: Carla Fernandes Dionizio | I86: 19/10/2026 a 23/10/2026 | K86: A Contatar
A87: 5251 | B87: A P Capital Ltda | C87: Curitiba | D87: PR | E87: Treinamento Nova Loja (Pizza Hut) | H87: Roberta de Cássia Martareli | I87: 30/11/2026 a 04/12/2026 | K87: A Contatar
A88: 681535 | B88: Posto De Servicos Rosario Ltda | C88: Curitiba | D88: PR | E88: Treinamento Nova Loja (Pizza Hut) | H88: Roberta de Cássia Martareli | I88: 23/11/2026 a 27/11/2026 | K88: A Contatar
A89: 23352 | B89: A P CRUZEIRO DO SUL LTDA | C89: Curitiba | D89: PR | E89: Treinamento Nova Loja (Implantação) | H89: Betânia Cayret Pregnolato | I89: 23/11/2026 a 27/11/2026 | K89: A Contatar
A90: 651042 | B90: Cezar Comercio De Combustiveis Ltda Epp | C90: Foz Do Iguacu | D90: PR | E90: Retreinamento | F90: 45666 | G90: 568 | H90: Bruno Souza | I90: 08/03/2027 a 12/03/2027 | K90: A Contatar
A91: 19669 | B91: Delomeg Conveniencias Ltda | C91: Foz Do Iguacu | D91: PR | E91: Treinamento Nova Loja (Pizza Hut) | H91: Carla Fernandes Dionizio | I91: 01/03/2027 a 05/03/2027 | K91: A Contatar
A92: 19669 | B92: DELOMEG CONVENIÊNCIA LTDA | C92: Foz Do Iguacu | D92: PR | E92: Treinamento Nova Loja (Implantação) | H92: Carla Fernandes Dionizio | I92: 08/03/2027 a 12/03/2027 | K92: A Contatar
A93: 20699 | B93: BIA CONVENIENCIAS LTDA. | C93: Foz Do Iguacu | D93: PR | E93: Treinamento Nova Loja (Implantação) | H93: Bruno Souza | I93: 15/03/2027 a 19/03/2027 | K93: A Contatar
A94: 21379 | B94: Auto Posto Salvaro Ii Ltda | C94: Guarapuava | D94: PR | E94: Treinamento Nova Loja (Pizza Hut) | H94: Bruno Souza | I94: 14/12/2026 a 18/12/2026 | K94: A Contatar
A95: 620581 | B95: Auto Posto Salvaro Ltda | C95: Guarapuava | D95: PR | E95: Treinamento Nova Loja (Pizza Hut) | H95: Isabela Paim Ricardo | I95: 08/03/2027 a 12/03/2027 | K95: A Contatar
A96: 652471 | B96: D S R Pegoraro Com De Combustivel Ltda | C96: Ibema | D96: PR | E96: Retreinamento | F96: 45569 | G96: 665 | H96: Carla Fernandes Dionizio | I96: 11/01/2027 a 15/01/2027 | K96: A Contatar
A97: 20941 | B97: Auto Posto Ibipora Ltda - Epp | C97: Ibipora | D97: PR | E97: Retreinamento | F97: 45590 | G97: 644 | H97: Roberta de Cássia Martareli | I97: 09/11/2026 a 13/11/2026 | K97: A Contatar
A98: 685698 | B98: Auto Posto Palestra Ltda | C98: Iguaracu | D98: PR | E98: Retreinamento | F98: 45539 | G98: 695 | H98: Bruno Souza | I98: 09/11/2026 a 13/11/2026 | K98: A Contatar
A99: 667729 | B99: Auto Posto Lalaco Ltda - Epp | C99: Laranjeiras Do Sul | D99: PR | E99: Treinamento Nova Loja (Implantação) | H99: Bruno Souza | I99: 04/01/2027 a 08/01/2027 | K99: A Contatar
A100: 22755 | B100: Auto Posto Bs Premium Ltda | C100: Londrina | D100: PR | E100: Retreinamento | F100: 45842 | G100: 392 | H100: Bruno Souza | I100: 09/11/2026 a 13/11/2026 | K100: A Contatar
...

Sheet Qualidade_dos_Dados
A1: Categoria | B1: Detalhe | C1: Impacto
A2: Instrutor não cadastrado | B2: William Nunes aparece em 30 treinamentos no histórico mas não existe no cadastro 2026_AMPM-instrutores.xlsx | C2: Custos e histórico dele ficam fora dos totais por instrutor
A3: Cidade não geocodificada | B3: Instrutor: Lucas Silva dos Santos — cidade 'monte carlo' UF informada 'MG': Cidade existe no IBGE apenas em: SC (confira se a UF do cadastro esta certa) | C3: Não entra no cálculo de distância/proximidade
A4: Cidade não geocodificada | B4: Previsao PV 679889.0 — cidade '' UF informada 'RJ': Cidade nao encontrada na base IBGE (nome pode estar diferente/abreviado) | C4: Não entra no cálculo de distância/proximidade
A5: Cidade não geocodificada | B5: Previsao PV 40954.0 — cidade '' UF informada '-': Cidade nao encontrada na base IBGE (nome pode estar diferente/abreviado) | C5: Não entra no cálculo de distância/proximidade
A6: Cidade não geocodificada | B6: Previsao PV 664984.0 — cidade '' UF informada 'MT': Cidade nao encontrada na base IBGE (nome pode estar diferente/abreviado) | C6: Não entra no cálculo de distância/proximidade
A7: Cidade não geocodificada | B7: Previsao PV 999999455.0 — cidade '' UF informada '-': Cidade nao encontrada na base IBGE (nome pode estar diferente/abreviado) | C7: Não entra no cálculo de distância/proximidade
A8: Cidade não geocodificada | B8: Previsao PV 100050.0 — cidade '' UF informada 'SP ': Cidade nao encontrada na base IBGE (nome pode estar diferente/abreviado) | C8: Não entra no cálculo de distância/proximidade
A9: Cidade não geocodificada | B9: Previsao PV 42249.0 — cidade '' UF informada '-': Cidade nao encontrada na base IBGE (nome pode estar diferente/abreviado) | C9: Não entra no cálculo de distância/proximidade
A10: Cidade não geocodificada | B10: Previsao PV 16372.0 — cidade '' UF informada '-': Cidade nao encontrada na base IBGE (nome pode estar diferente/abreviado) | C10: Não entra no cálculo de distância/proximidade
A11: Cidade não geocodificada | B11: Previsao PV 632227.0 — cidade '' UF informada 'SC': Cidade nao encontrada na base IBGE (nome pode estar diferente/abreviado) | C11: Não entra no cálculo de distância/proximidade
A12: Cidade não geocodificada | B12: Previsao PV 635097.0 — cidade '' UF informada '-': Cidade nao encontrada na base IBGE (nome pode estar diferente/abreviado) | C12: Não entra no cálculo de distância/proximidade
... A45: Cobertura do histórico | B45: 1.186 das 1.566 lojas ativas não têm NENHUM registro no histórico de treinamentos enviado — não foram tratadas como "atrasadas" porque provavelmente o histórico enviado não cobre a vida toda da loja, só cobrem um recorte (jun/2024 a jul/2026) | C45: Se a intenção for testar TODA a rede e não só quem já treinou antes, essa lista de 1.186 precisa ser revisada com a área de operações
